{
"meta":{"test_sets":[],"test_metrics":[],"learn_metrics":[{"best_value":"Min","name":"RMSE"}],"launch_mode":"Train","parameters":"","iteration_count":1000,"learn_sets":["learn"],"name":"experiment"},
"iterations":[
{"learn":[6.643932147],"iteration":0,"passed_time":0.001609249436,"remaining_time":1.607640186},
{"learn":[6.602206408],"iteration":1,"passed_time":0.002964739962,"remaining_time":1.479405241},
{"learn":[6.56119221],"iteration":2,"passed_time":0.003921834289,"remaining_time":1.303356262},
{"learn":[6.534189887],"iteration":3,"passed_time":0.005090808337,"remaining_time":1.267611276},
{"learn":[6.487922105],"iteration":4,"passed_time":0.006357632731,"remaining_time":1.265168914},
{"learn":[6.437173342],"iteration":5,"passed_time":0.007433819806,"remaining_time":1.231536148},
{"learn":[6.400499255],"iteration":6,"passed_time":0.008551312655,"remaining_time":1.213064781},
{"learn":[6.373533716],"iteration":7,"passed_time":0.009782366487,"remaining_time":1.213013444},
{"learn":[6.348416343],"iteration":8,"passed_time":0.01161961411,"remaining_time":1.27944862},
{"learn":[6.323600181],"iteration":9,"passed_time":0.01253579708,"remaining_time":1.241043911},
{"learn":[6.294625672],"iteration":10,"passed_time":0.01354220275,"remaining_time":1.217567138},
{"learn":[6.246145813],"iteration":11,"passed_time":0.01471481468,"remaining_time":1.211519742},
{"learn":[6.217592623],"iteration":12,"passed_time":0.01617696682,"remaining_time":1.228205096},
{"learn":[6.185770231],"iteration":13,"passed_time":0.01719706813,"remaining_time":1.211164941},
{"learn":[6.156599799],"iteration":14,"passed_time":0.01867270663,"remaining_time":1.226174402},
{"learn":[6.111085709],"iteration":15,"passed_time":0.02010869021,"remaining_time":1.236684448},
{"learn":[6.082876179],"iteration":16,"passed_time":0.0214617901,"remaining_time":1.240996451},
{"learn":[6.055491087],"iteration":17,"passed_time":0.02259950808,"remaining_time":1.232928719},
{"learn":[6.035043656],"iteration":18,"passed_time":0.02391629006,"remaining_time":1.234835818},
{"learn":[6.014900705],"iteration":19,"passed_time":0.0250846516,"remaining_time":1.229147928},
{"learn":[5.993606595],"iteration":20,"passed_time":0.02638557959,"remaining_time":1.230070591},
{"learn":[5.971791661],"iteration":21,"passed_time":0.02757819779,"remaining_time":1.225976247},
{"learn":[5.950846425],"iteration":22,"passed_time":0.02865123108,"remaining_time":1.217054468},
{"learn":[5.926458541],"iteration":23,"passed_time":0.0298782139,"remaining_time":1.215047365},
{"learn":[5.909898908],"iteration":24,"passed_time":0.03117447063,"remaining_time":1.215804355},
{"learn":[5.89175098],"iteration":25,"passed_time":0.03233023775,"remaining_time":1.211140445},
{"learn":[5.87403601],"iteration":26,"passed_time":0.03377695982,"remaining_time":1.217221552},
{"learn":[5.85763938],"iteration":27,"passed_time":0.03533092651,"remaining_time":1.226487877},
{"learn":[5.837626757],"iteration":28,"passed_time":0.0367192224,"remaining_time":1.22946086},
{"learn":[5.821183756],"iteration":29,"passed_time":0.0382503993,"remaining_time":1.236762911},
{"learn":[5.802568747],"iteration":30,"passed_time":0.03970327983,"remaining_time":1.241047683},
{"learn":[5.772324857],"iteration":31,"passed_time":0.04123465414,"remaining_time":1.247348288},
{"learn":[5.750999238],"iteration":32,"passed_time":0.04276182596,"remaining_time":1.253051082},
{"learn":[5.737695349],"iteration":33,"passed_time":0.04441952585,"remaining_time":1.262037117},
{"learn":[5.717128872],"iteration":34,"passed_time":0.04584953497,"remaining_time":1.264137178},
{"learn":[5.709630034],"iteration":35,"passed_time":0.04774625863,"remaining_time":1.278538703},
{"learn":[5.699059792],"iteration":36,"passed_time":0.04954852183,"remaining_time":1.289600717},
{"learn":[5.686400704],"iteration":37,"passed_time":0.05121652057,"remaining_time":1.296586652},
{"learn":[5.672655387],"iteration":38,"passed_time":0.05300881725,"remaining_time":1.306191625},
{"learn":[5.653566482],"iteration":39,"passed_time":0.05465011964,"remaining_time":1.311602871},
{"learn":[5.641989176],"iteration":40,"passed_time":0.05618489265,"remaining_time":1.314178343},
{"learn":[5.629947852],"iteration":41,"passed_time":0.05746973591,"remaining_time":1.310857309},
{"learn":[5.618801683],"iteration":42,"passed_time":0.05903248779,"remaining_time":1.313816065},
{"learn":[5.605708294],"iteration":43,"passed_time":0.06079151225,"remaining_time":1.320833766},
{"learn":[5.597676718],"iteration":44,"passed_time":0.0621358415,"remaining_time":1.318660636},
{"learn":[5.590460841],"iteration":45,"passed_time":0.06335276504,"remaining_time":1.313881258},
{"learn":[5.585177206],"iteration":46,"passed_time":0.06456149135,"remaining_time":1.309087261},
{"learn":[5.575486795],"iteration":47,"passed_time":0.06612272116,"remaining_time":1.31143397},
{"learn":[5.565834192],"iteration":48,"passed_time":0.06746325155,"remaining_time":1.3093378},
{"learn":[5.553010517],"iteration":49,"passed_time":0.0688407641,"remaining_time":1.307974518},
{"learn":[5.538083812],"iteration":50,"passed_time":0.07025233809,"remaining_time":1.307244487},
{"learn":[5.526806668],"iteration":51,"passed_time":0.07156015664,"remaining_time":1.304596702},
{"learn":[5.517441723],"iteration":52,"passed_time":0.07277771875,"remaining_time":1.300386786},
{"learn":[5.504348148],"iteration":53,"passed_time":0.07415864611,"remaining_time":1.299149615},
{"learn":[5.496634828],"iteration":54,"passed_time":0.07539053438,"remaining_time":1.295346454},
{"learn":[5.485290708],"iteration":55,"passed_time":0.07651208828,"remaining_time":1.289775202},
{"learn":[5.475377018],"iteration":56,"passed_time":0.07771573742,"remaining_time":1.285718252},
{"learn":[5.468597569],"iteration":57,"passed_time":0.07880025664,"remaining_time":1.279824858},
{"learn":[5.454249523],"iteration":58,"passed_time":0.07982207359,"remaining_time":1.273094428},
{"learn":[5.441449825],"iteration":59,"passed_time":0.08103522547,"remaining_time":1.269551866},
{"learn":[5.430315723],"iteration":60,"passed_time":0.08233046723,"remaining_time":1.267349323},
{"learn":[5.418011158],"iteration":61,"passed_time":0.08355213178,"remaining_time":1.264062897},
{"learn":[5.405214132],"iteration":62,"passed_time":0.08480157819,"remaining_time":1.261255218},
{"learn":[5.397025676],"iteration":63,"passed_time":0.08591594792,"remaining_time":1.256520738},
{"learn":[5.389248131],"iteration":64,"passed_time":0.08696075972,"remaining_time":1.250897082},
{"learn":[5.373499886],"iteration":65,"passed_time":0.08808521404,"remaining_time":1.246539241},
{"learn":[5.364041972],"iteration":66,"passed_time":0.08928039842,"remaining_time":1.243262862},
{"learn":[5.353820689],"iteration":67,"passed_time":0.09036110305,"remaining_time":1.238478648},
{"learn":[5.344375308],"iteration":68,"passed_time":0.09142075002,"remaining_time":1.233517656},
{"learn":[5.334528683],"iteration":69,"passed_time":0.09244364021,"remaining_time":1.228179791},
{"learn":[5.319453599],"iteration":70,"passed_time":0.09350114456,"remaining_time":1.223416384},
{"learn":[5.309165174],"iteration":71,"passed_time":0.09460844243,"remaining_time":1.219397702},
{"learn":[5.306412863],"iteration":72,"passed_time":0.09571382458,"remaining_time":1.215434457},
{"learn":[5.284501731],"iteration":73,"passed_time":0.09691438587,"remaining_time":1.212739477},
{"learn":[5.273179207],"iteration":74,"passed_time":0.09812730547,"remaining_time":1.210236767},
{"learn":[5.260732991],"iteration":75,"passed_time":0.09931290662,"remaining_time":1.207435865},
{"learn":[5.245255339],"iteration":76,"passed_time":0.1003760309,"remaining_time":1.203208786},
{"learn":[5.233157779],"iteration":77,"passed_time":0.1014945924,"remaining_time":1.19971813},
{"learn":[5.224590824],"iteration":78,"passed_time":0.1025787091,"remaining_time":1.195885963},
{"learn":[5.217261215],"iteration":79,"passed_time":0.1036271488,"remaining_time":1.191712212},
{"learn":[5.205476976],"iteration":80,"passed_time":0.1047442408,"remaining_time":1.188394534},
{"learn":[5.19362921],"iteration":81,"passed_time":0.1058888336,"remaining_time":1.185438405},
{"learn":[5.18902061],"iteration":82,"passed_time":0.1069368149,"remaining_time":1.181458545},
{"learn":[5.174854965],"iteration":83,"passed_time":0.1079566908,"remaining_time":1.177242009},
{"learn":[5.16246828],"iteration":84,"passed_time":0.1089236424,"remaining_time":1.172530974},
{"learn":[5.153429917],"iteration":85,"passed_time":0.1100221927,"remaining_time":1.169305629},
{"learn":[5.143387308],"iteration":86,"passed_time":0.1110769648,"remaining_time":1.165669757},
{"learn":[5.129356634],"iteration":87,"passed_time":0.112212897,"remaining_time":1.16293366},
{"learn":[5.114969391],"iteration":88,"passed_time":0.1133201278,"remaining_time":1.159939735},
{"learn":[5.110414741],"iteration":89,"passed_time":0.114371964,"remaining_time":1.156427636},
{"learn":[5.101288888],"iteration":90,"passed_time":0.1152821882,"remaining_time":1.151555044},
{"learn":[5.088956559],"iteration":91,"passed_time":0.1162407172,"remaining_time":1.147245339},
{"learn":[5.080310152],"iteration":92,"passed_time":0.1172629036,"remaining_time":1.143628533},
{"learn":[5.069667211],"iteration":93,"passed_time":0.1181947248,"remaining_time":1.139195964},
{"learn":[5.058911159],"iteration":94,"passed_time":0.1191362246,"remaining_time":1.134929298},
{"learn":[5.045403534],"iteration":95,"passed_time":0.1200204144,"remaining_time":1.130192236},
{"learn":[5.036271857],"iteration":96,"passed_time":0.1209707409,"remaining_time":1.126150299},
{"learn":[5.021231461],"iteration":97,"passed_time":0.1219022335,"remaining_time":1.121998109},
{"learn":[5.01276242],"iteration":98,"passed_time":0.122758208,"remaining_time":1.117223691},
{"learn":[4.999492002],"iteration":99,"passed_time":0.1235990398,"remaining_time":1.112391358},
{"learn":[4.984348955],"iteration":100,"passed_time":0.1245391153,"remaining_time":1.108521432},
{"learn":[4.97656052],"iteration":101,"passed_time":0.125524532,"remaining_time":1.105108134},
{"learn":[4.966272024],"iteration":102,"passed_time":0.1265254055,"remaining_time":1.10187659},
{"learn":[4.959308931],"iteration":103,"passed_time":0.1275537446,"remaining_time":1.098924569},
{"learn":[4.951919087],"iteration":104,"passed_time":0.1285134979,"remaining_time":1.095424577},
{"learn":[4.941586507],"iteration":105,"passed_time":0.1295761316,"remaining_time":1.092840204},
{"learn":[4.933860229],"iteration":106,"passed_time":0.1304763118,"remaining_time":1.088928471},
{"learn":[4.927129314],"iteration":107,"passed_time":0.1314174881,"remaining_time":1.085411106},
{"learn":[4.919408181],"iteration":108,"passed_time":0.1322662842,"remaining_time":1.081185864},
{"learn":[4.913784654],"iteration":109,"passed_time":0.1331694273,"remaining_time":1.07746173},
{"learn":[4.906774962],"iteration":110,"passed_time":0.1340734674,"remaining_time":1.073795608},
{"learn":[4.893824994],"iteration":111,"passed_time":0.1350994201,"remaining_time":1.071145403},
{"learn":[4.889816213],"iteration":112,"passed_time":0.1360172383,"remaining_time":1.067675136},
{"learn":[4.882884722],"iteration":113,"passed_time":0.1369084233,"remaining_time":1.064042658},
{"learn":[4.877323414],"iteration":114,"passed_time":0.1377758484,"remaining_time":1.060275007},
{"learn":[4.873112819],"iteration":115,"passed_time":0.1386381373,"remaining_time":1.056518219},
{"learn":[4.86892638],"iteration":116,"passed_time":0.1395225739,"remaining_time":1.052978058},
{"learn":[4.859782269],"iteration":117,"passed_time":0.1404641328,"remaining_time":1.049909874},
{"learn":[4.853213781],"iteration":118,"passed_time":0.1414262318,"remaining_time":1.047029498},
{"learn":[4.848518214],"iteration":119,"passed_time":0.1423005832,"remaining_time":1.04353761},
{"learn":[4.839263718],"iteration":120,"passed_time":0.143289395,"remaining_time":1.040920481},
{"learn":[4.828594738],"iteration":121,"passed_time":0.1442715153,"remaining_time":1.038281889},
{"learn":[4.815344766],"iteration":122,"passed_time":0.1452253972,"remaining_time":1.035468889},
{"learn":[4.805963873],"iteration":123,"passed_time":0.1460667994,"remaining_time":1.03189126},
{"learn":[4.793416438],"iteration":124,"passed_time":0.1470425715,"remaining_time":1.029298},
{"learn":[4.785841511],"iteration":125,"passed_time":0.1480123921,"remaining_time":1.026689132},
{"learn":[4.779759084],"iteration":126,"passed_time":0.1489514051,"remaining_time":1.023894304},
{"learn":[4.771279942],"iteration":127,"passed_time":0.149825127,"remaining_time":1.020683678},
{"learn":[4.765087721],"iteration":128,"passed_time":0.1506577249,"remaining_time":1.017231615},
{"learn":[4.759661514],"iteration":129,"passed_time":0.1515518505,"remaining_time":1.014231615},
{"learn":[4.751618164],"iteration":130,"passed_time":0.1524042856,"remaining_time":1.010987208},
{"learn":[4.746245454],"iteration":131,"passed_time":0.153380513,"remaining_time":1.008593071},
{"learn":[4.737413575],"iteration":132,"passed_time":0.1543296351,"remaining_time":1.006043561},
{"learn":[4.733230679],"iteration":133,"passed_time":0.1551823354,"remaining_time":1.002894795},
{"learn":[4.727518358],"iteration":134,"passed_time":0.1561057643,"remaining_time":1.00023323},
{"learn":[4.721274825],"iteration":135,"passed_time":0.1571304889,"remaining_time":0.9982407533},
{"learn":[4.712065584],"iteration":136,"passed_time":0.1580828055,"remaining_time":0.9958062855},
{"learn":[4.703435405],"iteration":137,"passed_time":0.1589938472,"remaining_time":0.9931354806},
{"learn":[4.697361177],"iteration":138,"passed_time":0.1599862039,"remaining_time":0.9909936801},
{"learn":[4.688795169],"iteration":139,"passed_time":0.1610133586,"remaining_time":0.9890820603},
{"learn":[4.679464308],"iteration":140,"passed_time":0.1620487509,"remaining_time":0.9872331703},
{"learn":[4.673008291],"iteration":141,"passed_time":0.1630361262,"remaining_time":0.9851056074},
{"learn":[4.660430315],"iteration":142,"passed_time":0.1639034087,"remaining_time":0.9822742744},
{"learn":[4.655192284],"iteration":143,"passed_time":0.1647981484,"remaining_time":0.9796334377},
{"learn":[4.646440953],"iteration":144,"passed_time":0.1657175802,"remaining_time":0.9771622833},
{"learn":[4.634615779],"iteration":145,"passed_time":0.1666646777,"remaining_time":0.9748742108},
{"learn":[4.623432558],"iteration":146,"passed_time":0.1675397696,"remaining_time":0.972186554},
{"learn":[4.618288125],"iteration":147,"passed_time":0.1684071165,"remaining_time":0.9694788057},
{"learn":[4.614491182],"iteration":148,"passed_time":0.1692316704,"remaining_time":0.9665513525},
{"learn":[4.60849246],"iteration":149,"passed_time":0.1700266966,"remaining_time":0.9634846139},
{"learn":[4.602900727],"iteration":150,"passed_time":0.1709074382,"remaining_time":0.9609299011},
{"learn":[4.595308859],"iteration":151,"passed_time":0.1718562008,"remaining_time":0.9587766992},
{"learn":[4.590252422],"iteration":152,"passed_time":0.1728055054,"remaining_time":0.9566422421},
{"learn":[4.579092221],"iteration":153,"passed_time":0.1738558888,"remaining_time":0.9550784539},
{"learn":[4.575221151],"iteration":154,"passed_time":0.1748853725,"remaining_time":0.9534073531},
{"learn":[4.565627258],"iteration":155,"passed_time":0.1758437627,"remaining_time":0.9513598445},
{"learn":[4.556382964],"iteration":156,"passed_time":0.1767414086,"remaining_time":0.9490000475},
{"learn":[4.543239964],"iteration":157,"passed_time":0.1776127365,"remaining_time":0.946518507},
{"learn":[4.535710339],"iteration":158,"passed_time":0.1784283358,"remaining_time":0.9437624553},
{"learn":[4.527095362],"iteration":159,"passed_time":0.1792680331,"remaining_time":0.9411571737},
{"learn":[4.520988648],"iteration":160,"passed_time":0.1801748482,"remaining_time":0.938923588},
{"learn":[4.51581104],"iteration":161,"passed_time":0.1811709631,"remaining_time":0.9371683153},
{"learn":[4.509964102],"iteration":162,"passed_time":0.1820428636,"remaining_time":0.9347845205},
{"learn":[4.502520961],"iteration":163,"passed_time":0.182964192,"remaining_time":0.9326711249},
{"learn":[4.498759485],"iteration":164,"passed_time":0.1837967108,"remaining_time":0.9301227488},
{"learn":[4.492498379],"iteration":165,"passed_time":0.1846162574,"remaining_time":0.9275298714},
{"learn":[4.487568313],"iteration":166,"passed_time":0.1854940791,"remaining_time":0.9252489093},
{"learn":[4.482419074],"iteration":167,"passed_time":0.1864610203,"remaining_time":0.9234260054},
{"learn":[4.475386477],"iteration":168,"passed_time":0.1874626513,"remaining_time":0.9217838059},
{"learn":[4.467272456],"iteration":169,"passed_time":0.1884272724,"remaining_time":0.9199684477},
{"learn":[4.461854402],"iteration":170,"passed_time":0.189371161,"remaining_time":0.9180625289},
{"learn":[4.455513382],"iteration":171,"passed_time":0.1903733527,"remaining_time":0.9164484651},
{"learn":[4.447537461],"iteration":172,"passed_time":0.1913542579,"remaining_time":0.9147397182},
{"learn":[4.440717529],"iteration":173,"passed_time":0.1923620135,"remaining_time":0.9131667998},
{"learn":[4.428554304],"iteration":174,"passed_time":0.1933310694,"remaining_time":0.9114178988},
{"learn":[4.421420516],"iteration":175,"passed_time":0.1942502958,"remaining_time":0.9094445667},
{"learn":[4.417557697],"iteration":176,"passed_time":0.1951516834,"remaining_time":0.9074002004},
{"learn":[4.409080353],"iteration":177,"passed_time":0.1960561597,"remaining_time":0.9053829398},
{"learn":[4.403968312],"iteration":178,"passed_time":0.1970717642,"remaining_time":0.9038878121},
{"learn":[4.395832868],"iteration":179,"passed_time":0.1980358364,"remaining_time":0.9021632549},
{"learn":[4.389416004],"iteration":180,"passed_time":0.198897926,"remaining_time":0.8999856432},
{"learn":[4.380869661],"iteration":181,"passed_time":0.1998232599,"remaining_time":0.8981067394},
{"learn":[4.375975603],"iteration":182,"passed_time":0.200724682,"remaining_time":0.8961315038},
{"learn":[4.372101181],"iteration":183,"passed_time":0.2016572621,"remaining_time":0.8943061188},
{"learn":[4.36599663],"iteration":184,"passed_time":0.2025975729,"remaining_time":0.8925244429},
{"learn":[4.362262895],"iteration":185,"passed_time":0.2035227703,"remaining_time":0.8906856722},
{"learn":[4.354281302],"iteration":186,"passed_time":0.2044009883,"remaining_time":0.8886524252},
{"learn":[4.347717068],"iteration":187,"passed_time":0.2053761494,"remaining_time":0.8870501773},
{"learn":[4.338320317],"iteration":188,"passed_time":0.2062864798,"remaining_time":0.8851763763},
{"learn":[4.330307409],"iteration":189,"passed_time":0.2073919582,"remaining_time":0.8841446638},
{"learn":[4.32297562],"iteration":190,"passed_time":0.2083675762,"remaining_time":0.882562142},
{"learn":[4.315356133],"iteration":191,"passed_time":0.2092466359,"remaining_time":0.8805795928},
{"learn":[4.31028939],"iteration":192,"passed_time":0.2101439192,"remaining_time":0.8786846777},
{"learn":[4.305397355],"iteration":193,"passed_time":0.2110325016,"remaining_time":0.8767638984},
{"learn":[4.298857175],"iteration":194,"passed_time":0.2119000103,"remaining_time":0.8747667091},
{"learn":[4.287961216],"iteration":195,"passed_time":0.2127806707,"remaining_time":0.872834996},
{"learn":[4.28073023],"iteration":196,"passed_time":0.2137465981,"remaining_time":0.8712615141},
{"learn":[4.270681632],"iteration":197,"passed_time":0.2147078884,"remaining_time":0.8696753864},
{"learn":[4.265017297],"iteration":198,"passed_time":0.2157662939,"remaining_time":0.8684864392},
{"learn":[4.256377056],"iteration":199,"passed_time":0.216685938,"remaining_time":0.8667437521},
{"learn":[4.244677319],"iteration":200,"passed_time":0.2176621363,"remaining_time":0.8652340643},
{"learn":[4.23622855],"iteration":201,"passed_time":0.2185597408,"remaining_time":0.8634191742},
{"learn":[4.226132123],"iteration":202,"passed_time":0.2195076398,"remaining_time":0.861810783},
{"learn":[4.221553144],"iteration":203,"passed_time":0.2204708114,"remaining_time":0.86026846},
{"learn":[4.210899739],"iteration":204,"passed_time":0.2214161193,"remaining_time":0.8586625112},
{"learn":[4.202743758],"iteration":205,"passed_time":0.2224527009,"remaining_time":0.857414779},
{"learn":[4.196699613],"iteration":206,"passed_time":0.223433465,"remaining_time":0.8559552549},
{"learn":[4.187915069],"iteration":207,"passed_time":0.2243382671,"remaining_time":0.8542110939},
{"learn":[4.179406086],"iteration":208,"passed_time":0.2252515998,"remaining_time":0.8525072511},
{"learn":[4.172341005],"iteration":209,"passed_time":0.2261673731,"remaining_time":0.8508201177},
{"learn":[4.163915084],"iteration":210,"passed_time":0.2270828285,"remaining_time":0.8491391076},
{"learn":[4.15607583],"iteration":211,"passed_time":0.2279520536,"remaining_time":0.8472934823},
{"learn":[4.151626438],"iteration":212,"passed_time":0.2288797394,"remaining_time":0.8456730276},
{"learn":[4.143701519],"iteration":213,"passed_time":0.2298543224,"remaining_time":0.8442312965},
{"learn":[4.136608321],"iteration":214,"passed_time":0.2308324967,"remaining_time":0.8428070227},
{"learn":[4.130665365],"iteration":215,"passed_time":0.2318331697,"remaining_time":0.8414685419},
{"learn":[4.126523958],"iteration":216,"passed_time":0.2327386399,"remaining_time":0.8397896545},
{"learn":[4.121199163],"iteration":217,"passed_time":0.2339251199,"remaining_time":0.8391258889},
{"learn":[4.114140951],"iteration":218,"passed_time":0.2348342632,"remaining_time":0.8374683086},
{"learn":[4.107767605],"iteration":219,"passed_time":0.235706227,"remaining_time":0.8356857138},
{"learn":[4.100668227],"iteration":220,"passed_time":0.2366472523,"remaining_time":0.8341547943},
{"learn":[4.092836931],"iteration":221,"passed_time":0.2377011724,"remaining_time":0.8330248294},
{"learn":[4.089900108],"iteration":222,"passed_time":0.2386976483,"remaining_time":0.8316953936},
{"learn":[4.085152658],"iteration":223,"passed_time":0.239539798,"remaining_time":0.8298343002},
{"learn":[4.077440623],"iteration":224,"passed_time":0.2405516952,"remaining_time":0.82856695},
{"learn":[4.069605381],"iteration":225,"passed_time":0.2414621432,"remaining_time":0.8269544197},
{"learn":[4.064455375],"iteration":226,"passed_time":0.242275672,"remaining_time":0.8250180372},
{"learn":[4.058408889],"iteration":227,"passed_time":0.2432202873,"remaining_time":0.8235353586},
{"learn":[4.052208926],"iteration":228,"passed_time":0.2441637956,"remaining_time":0.8220536523},
{"learn":[4.049342314],"iteration":229,"passed_time":0.2450216443,"remaining_time":0.8202898528},
{"learn":[4.04437146],"iteration":230,"passed_time":0.2459757125,"remaining_time":0.8188542118},
{"learn":[4.037202178],"iteration":231,"passed_time":0.2468551954,"remaining_time":0.8171758194},
{"learn":[4.029568962],"iteration":232,"passed_time":0.2477067512,"remaining_time":0.8154123527},
{"learn":[4.022781564],"iteration":233,"passed_time":0.2486204435,"remaining_time":0.8138600843},
{"learn":[4.018635393],"iteration":234,"passed_time":0.2495694115,"remaining_time":0.8124280843},
{"learn":[4.010665967],"iteration":235,"passed_time":0.2503826014,"remaining_time":0.810560625},
{"learn":[4.00428297],"iteration":236,"passed_time":0.2513433605,"remaining_time":0.8091771478},
{"learn":[4.000357542],"iteration":237,"passed_time":0.2522576975,"remaining_time":0.8076485944},
{"learn":[3.993357842],"iteration":238,"passed_time":0.2531549033,"remaining_time":0.8060706336},
{"learn":[3.986844948],"iteration":239,"passed_time":0.2541449698,"remaining_time":0.8047924042},
{"learn":[3.980857603],"iteration":240,"passed_time":0.2551827086,"remaining_time":0.8036667045},
{"learn":[3.975605717],"iteration":241,"passed_time":0.2559769765,"remaining_time":0.8017791249},
{"learn":[3.967159468],"iteration":242,"passed_time":0.25689838,"remaining_time":0.8002965995},
{"learn":[3.95992149],"iteration":243,"passed_time":0.2578134913,"remaining_time":0.798799178},
{"learn":[3.956007112],"iteration":244,"passed_time":0.258708888,"remaining_time":0.7972457569},
{"learn":[3.949114137],"iteration":245,"passed_time":0.2595650794,"remaining_time":0.7955775197},
{"learn":[3.94553906],"iteration":246,"passed_time":0.2604979776,"remaining_time":0.794149705},
{"learn":[3.936726498],"iteration":247,"passed_time":0.2614099366,"remaining_time":0.7926623885},
{"learn":[3.930840141],"iteration":248,"passed_time":0.2622942828,"remaining_time":0.7910964113},
{"learn":[3.923973665],"iteration":249,"passed_time":0.2631561562,"remaining_time":0.7894684687},
{"learn":[3.919967379],"iteration":250,"passed_time":0.2639687413,"remaining_time":0.7876995507},
{"learn":[3.914511951],"iteration":251,"passed_time":0.2648642813,"remaining_time":0.7861844541},
{"learn":[3.909664355],"iteration":252,"passed_time":0.265814397,"remaining_time":0.7848353934},
{"learn":[3.902952268],"iteration":253,"passed_time":0.2667804049,"remaining_time":0.7835361498},
{"learn":[3.898350819],"iteration":254,"passed_time":0.2676661126,"remaining_time":0.7820049171},
{"learn":[3.892914672],"iteration":255,"passed_time":0.2685972825,"remaining_time":0.7806108523},
{"learn":[3.887800591],"iteration":256,"passed_time":0.2694974417,"remaining_time":0.779130736},
{"learn":[3.881282345],"iteration":257,"passed_time":0.2703381133,"remaining_time":0.7774840313},
{"learn":[3.875275526],"iteration":258,"passed_time":0.2712996401,"remaining_time":0.7761893178},
{"learn":[3.872347868],"iteration":259,"passed_time":0.2721952974,"remaining_time":0.7747096927},
{"learn":[3.865726666],"iteration":260,"passed_time":0.2731521898,"remaining_time":0.7734079243},
{"learn":[3.859587904],"iteration":261,"passed_time":0.2740774569,"remaining_time":0.7720197069},
{"learn":[3.853017136],"iteration":262,"passed_time":0.2749220826,"remaining_time":0.7704090301},
{"learn":[3.849790985],"iteration":263,"passed_time":0.2758657132,"remaining_time":0.7690801702},
{"learn":[3.841778162],"iteration":264,"passed_time":0.2768910278,"remaining_time":0.7679807752},
{"learn":[3.838439288],"iteration":265,"passed_time":0.2779108531,"remaining_time":0.7668667902},
{"learn":[3.833574423],"iteration":266,"passed_time":0.2788797113,"remaining_time":0.7656135894},
{"learn":[3.830242891],"iteration":267,"passed_time":0.2798726275,"remaining_time":0.7644282214},
{"learn":[3.823704515],"iteration":268,"passed_time":0.2809491074,"remaining_time":0.7634713663},
{"learn":[3.821026573],"iteration":269,"passed_time":0.2818845063,"remaining_time":0.7621321837},
{"learn":[3.817488675],"iteration":270,"passed_time":0.2828266804,"remaining_time":0.7608142066},
{"learn":[3.810903887],"iteration":271,"passed_time":0.283750967,"remaining_time":0.7594511176},
{"learn":[3.805618885],"iteration":272,"passed_time":0.2846998825,"remaining_time":0.75815683},
{"learn":[3.799874671],"iteration":273,"passed_time":0.2857770443,"remaining_time":0.7572048693},
{"learn":[3.794100605],"iteration":274,"passed_time":0.2866820047,"remaining_time":0.7557980124},
{"learn":[3.786339473],"iteration":275,"passed_time":0.2876588837,"remaining_time":0.7545834486},
{"learn":[3.780179726],"iteration":276,"passed_time":0.2885663888,"remaining_time":0.7531895275},
{"learn":[3.775450642],"iteration":277,"passed_time":0.2895190791,"remaining_time":0.7519164571},
{"learn":[3.770782548],"iteration":278,"passed_time":0.2905402111,"remaining_time":0.7508225526},
{"learn":[3.765161582],"iteration":279,"passed_time":0.291413539,"remaining_time":0.7493491002},
{"learn":[3.759629983],"iteration":280,"passed_time":0.2922234578,"remaining_time":0.7477176731},
{"learn":[3.750992909],"iteration":281,"passed_time":0.2931320315,"remaining_time":0.7463432575},
{"learn":[3.746531923],"iteration":282,"passed_time":0.2940839732,"remaining_time":0.7450820097},
{"learn":[3.741708325],"iteration":283,"passed_time":0.2949434027,"remaining_time":0.7435897053},
{"learn":[3.738354759],"iteration":284,"passed_time":0.2958484102,"remaining_time":0.7422161869},
{"learn":[3.733166993],"iteration":285,"passed_time":0.2968126093,"remaining_time":0.740993717},
{"learn":[3.730910155],"iteration":286,"passed_time":0.2976788654,"remaining_time":0.7395297248},
{"learn":[3.725460585],"iteration":287,"passed_time":0.2985235402,"remaining_time":0.7380165299},
{"learn":[3.721686591],"iteration":288,"passed_time":0.29933855,"remaining_time":0.7364349794},
{"learn":[3.718720826],"iteration":289,"passed_time":0.3003157284,"remaining_time":0.7352557488},
{"learn":[3.713954417],"iteration":290,"passed_time":0.3013043674,"remaining_time":0.7341058299},
{"learn":[3.71005368],"iteration":291,"passed_time":0.302343222,"remaining_time":0.7330787711},
{"learn":[3.70537501],"iteration":292,"passed_time":0.3032635729,"remaining_time":0.7317656862},
{"learn":[3.70102246],"iteration":293,"passed_time":0.30425692,"remaining_time":0.730630563},
{"learn":[3.696455671],"iteration":294,"passed_time":0.3053007801,"remaining_time":0.7296171185},
{"learn":[3.692491799],"iteration":295,"passed_time":0.3062393442,"remaining_time":0.7283530349},
{"learn":[3.688545095],"iteration":296,"passed_time":0.3071173177,"remaining_time":0.7269477251},
{"learn":[3.683320196],"iteration":297,"passed_time":0.3081256111,"remaining_time":0.7258529497},
{"learn":[3.679670762],"iteration":298,"passed_time":0.3091307998,"remaining_time":0.7247514738},
{"learn":[3.675381556],"iteration":299,"passed_time":0.3099736624,"remaining_time":0.7232718789},
{"learn":[3.66971608],"iteration":300,"passed_time":0.3109181811,"remaining_time":0.7220325866},
{"learn":[3.665120999],"iteration":301,"passed_time":0.3118550491,"remaining_time":0.7207775639},
{"learn":[3.660234931],"iteration":302,"passed_time":0.3127322338,"remaining_time":0.7193873497},
{"learn":[3.657062092],"iteration":303,"passed_time":0.3135601017,"remaining_time":0.7178876013},
{"learn":[3.650455508],"iteration":304,"passed_time":0.3144364439,"remaining_time":0.7165027164},
{"learn":[3.647747723],"iteration":305,"passed_time":0.3152452312,"remaining_time":0.7149679427},
{"learn":[3.643545329],"iteration":306,"passed_time":0.3161515665,"remaining_time":0.7136580963},
{"learn":[3.638258982],"iteration":307,"passed_time":0.3171408878,"remaining_time":0.7125373193},
{"learn":[3.632130299],"iteration":308,"passed_time":0.3180933994,"remaining_time":0.7113350776},
{"learn":[3.629274105],"iteration":309,"passed_time":0.3190570381,"remaining_time":0.7101592139},
{"learn":[3.62558525],"iteration":310,"passed_time":0.3199222486,"remaining_time":0.7087666535},
{"learn":[3.62205573],"iteration":311,"passed_time":0.3207898224,"remaining_time":0.7073826852},
{"learn":[3.618727658],"iteration":312,"passed_time":0.3216121133,"remaining_time":0.7059026257},
{"learn":[3.613848435],"iteration":313,"passed_time":0.3224952797,"remaining_time":0.7045597512},
{"learn":[3.609118515],"iteration":314,"passed_time":0.3233995804,"remaining_time":0.7032657543},
{"learn":[3.604435347],"iteration":315,"passed_time":0.3242918923,"remaining_time":0.7019482733},
{"learn":[3.600730664],"iteration":316,"passed_time":0.3251871212,"remaining_time":0.7006397595},
{"learn":[3.59862345],"iteration":317,"passed_time":0.3261266508,"remaining_time":0.6994288549},
{"learn":[3.595623009],"iteration":318,"passed_time":0.3270203633,"remaining_time":0.6981218414},
{"learn":[3.593303313],"iteration":319,"passed_time":0.3278877715,"remaining_time":0.6967615145},
{"learn":[3.589700737],"iteration":320,"passed_time":0.3287985048,"remaining_time":0.6954959026},
{"learn":[3.584868934],"iteration":321,"passed_time":0.3297609944,"remaining_time":0.6943414727},
{"learn":[3.579711321],"iteration":322,"passed_time":0.3306587492,"remaining_time":0.6930525485},
{"learn":[3.57502411],"iteration":323,"passed_time":0.3316335396,"remaining_time":0.6919267678},
{"learn":[3.571841293],"iteration":324,"passed_time":0.3326325522,"remaining_time":0.6908522238},
{"learn":[3.56821688],"iteration":325,"passed_time":0.3335800258,"remaining_time":0.689671587},
{"learn":[3.564973011],"iteration":326,"passed_time":0.3347619982,"remaining_time":0.6889749994},
{"learn":[3.562062995],"iteration":327,"passed_time":0.3357798158,"remaining_time":0.6879391349},
{"learn":[3.557470388],"iteration":328,"passed_time":0.3366868234,"remaining_time":0.6866773815},
{"learn":[3.553636775],"iteration":329,"passed_time":0.3376730829,"remaining_time":0.6855786835},
{"learn":[3.549519394],"iteration":330,"passed_time":0.3386240073,"remaining_time":0.6844092474},
{"learn":[3.545299051],"iteration":331,"passed_time":0.3395984903,"remaining_time":0.6832885287},
{"learn":[3.540679631],"iteration":332,"passed_time":0.3406428157,"remaining_time":0.6823085828},
{"learn":[3.534877296],"iteration":333,"passed_time":0.3416416808,"remaining_time":0.681237603},
{"learn":[3.531704589],"iteration":334,"passed_time":0.3425745177,"remaining_time":0.6800359828},
{"learn":[3.528741055],"iteration":335,"passed_time":0.3435068877,"remaining_time":0.67883504},
{"learn":[3.525861502],"iteration":336,"passed_time":0.3443549961,"remaining_time":0.6774699181},
{"learn":[3.524210007],"iteration":337,"passed_time":0.3454129593,"remaining_time":0.6765188729},
{"learn":[3.520957618],"iteration":338,"passed_time":0.3462989379,"remaining_time":0.6752318524},
{"learn":[3.517224388],"iteration":339,"passed_time":0.347307835,"remaining_time":0.6741857974},
{"learn":[3.512803906],"iteration":340,"passed_time":0.3483681808,"remaining_time":0.6732393875},
{"learn":[3.50857522],"iteration":341,"passed_time":0.3493957303,"remaining_time":0.6722292122},
{"learn":[3.507229497],"iteration":342,"passed_time":0.3504059606,"remaining_time":0.6711857612},
{"learn":[3.503063294],"iteration":343,"passed_time":0.3513667131,"remaining_time":0.6700481505},
{"learn":[3.498882523],"iteration":344,"passed_time":0.3524597082,"remaining_time":0.6691626344},
{"learn":[3.494322558],"iteration":345,"passed_time":0.3534058513,"remaining_time":0.6679983432},
{"learn":[3.490525198],"iteration":346,"passed_time":0.3544822189,"remaining_time":0.6670803716},
{"learn":[3.487188573],"iteration":347,"passed_time":0.3555059692,"remaining_time":0.6660629078},
{"learn":[3.484073473],"iteration":348,"passed_time":0.3565822211,"remaining_time":0.6651433407},
{"learn":[3.479587191],"iteration":349,"passed_time":0.3574596709,"remaining_time":0.6638536746},
{"learn":[3.474443472],"iteration":350,"passed_time":0.3583125108,"remaining_time":0.6625208533},
{"learn":[3.470315276],"iteration":351,"passed_time":0.3592458816,"remaining_time":0.6613390093},
{"learn":[3.465550951],"iteration":352,"passed_time":0.3601243649,"remaining_time":0.6600579719},
{"learn":[3.46176414],"iteration":353,"passed_time":0.3610255501,"remaining_time":0.6588206367},
{"learn":[3.457775868],"iteration":354,"passed_time":0.3619524954,"remaining_time":0.6576319986},
{"learn":[3.452838283],"iteration":355,"passed_time":0.3630012574,"remaining_time":0.656665196},
{"learn":[3.45069314],"iteration":356,"passed_time":0.3640283539,"remaining_time":0.655658912},
{"learn":[3.447022347],"iteration":357,"passed_time":0.3650567368,"remaining_time":0.6546548185},
{"learn":[3.441332103],"iteration":358,"passed_time":0.3659978518,"remaining_time":0.6534947716},
{"learn":[3.435928947],"iteration":359,"passed_time":0.3670136414,"remaining_time":0.6524686958},
{"learn":[3.431760876],"iteration":360,"passed_time":0.3680092844,"remaining_time":0.6514070159},
{"learn":[3.428909901],"iteration":361,"passed_time":0.3690880871,"remaining_time":0.650492264},
{"learn":[3.42339368],"iteration":362,"passed_time":0.3699917401,"remaining_time":0.6492692518},
{"learn":[3.420547217],"iteration":363,"passed_time":0.3709500276,"remaining_time":0.6481434548},
{"learn":[3.417129911],"iteration":364,"passed_time":0.3718172266,"remaining_time":0.6468601065},
{"learn":[3.414414533],"iteration":365,"passed_time":0.3726793752,"remaining_time":0.6455702838},
{"learn":[3.409430201],"iteration":366,"passed_time":0.3735463396,"remaining_time":0.6442910979},
{"learn":[3.406202106],"iteration":367,"passed_time":0.3744332071,"remaining_time":0.6430483339},
{"learn":[3.402848236],"iteration":368,"passed_time":0.3754465286,"remaining_time":0.6420237386},
{"learn":[3.398184901],"iteration":369,"passed_time":0.3763621228,"remaining_time":0.6408328037},
{"learn":[3.394433784],"iteration":370,"passed_time":0.3773350773,"remaining_time":0.6397406027},
{"learn":[3.391175093],"iteration":371,"passed_time":0.3783515898,"remaining_time":0.6387225763},
{"learn":[3.388415149],"iteration":372,"passed_time":0.3793009787,"remaining_time":0.6375917255},
{"learn":[3.384177218],"iteration":373,"passed_time":0.3802847195,"remaining_time":0.6365193433},
{"learn":[3.379551482],"iteration":374,"passed_time":0.381241562,"remaining_time":0.6354026033},
{"learn":[3.376949753],"iteration":375,"passed_time":0.3820632565,"remaining_time":0.6340624257},
{"learn":[3.373316398],"iteration":376,"passed_time":0.3829150883,"remaining_time":0.6327748011},
{"learn":[3.371370396],"iteration":377,"passed_time":0.3838113988,"remaining_time":0.631562672},
{"learn":[3.36391472],"iteration":378,"passed_time":0.3847056356,"remaining_time":0.6303488119},
{"learn":[3.35967985],"iteration":379,"passed_time":0.3855105233,"remaining_time":0.6289908537},
{"learn":[3.357230996],"iteration":380,"passed_time":0.3863253391,"remaining_time":0.6276519289},
{"learn":[3.354810711],"iteration":381,"passed_time":0.3872124136,"remaining_time":0.6264326482},
{"learn":[3.352941148],"iteration":382,"passed_time":0.3880801032,"remaining_time":0.6251838738},
{"learn":[3.350602228],"iteration":383,"passed_time":0.3889865412,"remaining_time":0.6239992432},
{"learn":[3.347875423],"iteration":384,"passed_time":0.3899222264,"remaining_time":0.6228627772},
{"learn":[3.344724696],"iteration":385,"passed_time":0.3908099793,"remaining_time":0.621651107},
{"learn":[3.342538542],"iteration":386,"passed_time":0.3917560351,"remaining_time":0.6205334612},
{"learn":[3.339270902],"iteration":387,"passed_time":0.3927200426,"remaining_time":0.6194450156},
{"learn":[3.335690879],"iteration":388,"passed_time":0.3937357746,"remaining_time":0.6184384532},
{"learn":[3.330347561],"iteration":389,"passed_time":0.3948481574,"remaining_time":0.6175830154},
{"learn":[3.325285416],"iteration":390,"passed_time":0.3959299345,"remaining_time":0.6166785936},
{"learn":[3.32018403],"iteration":391,"passed_time":0.3968946361,"remaining_time":0.6155916805},
{"learn":[3.317093649],"iteration":392,"passed_time":0.3978532483,"remaining_time":0.614495984},
{"learn":[3.312093447],"iteration":393,"passed_time":0.398785158,"remaining_time":0.6133599131},
{"learn":[3.308922111],"iteration":394,"passed_time":0.399701318,"remaining_time":0.6122007528},
{"learn":[3.305104933],"iteration":395,"passed_time":0.4006562018,"remaining_time":0.6111018836},
{"learn":[3.303244524],"iteration":396,"passed_time":0.4015079722,"remaining_time":0.6098471216},
{"learn":[3.300184511],"iteration":397,"passed_time":0.4023378011,"remaining_time":0.6085611967},
{"learn":[3.296775894],"iteration":398,"passed_time":0.4032929127,"remaining_time":0.6074662669},
{"learn":[3.292353956],"iteration":399,"passed_time":0.4040935074,"remaining_time":0.6061402611},
{"learn":[3.289343066],"iteration":400,"passed_time":0.4049688116,"remaining_time":0.6049284741},
{"learn":[3.286557943],"iteration":401,"passed_time":0.4058074188,"remaining_time":0.6036637722},
{"learn":[3.283836849],"iteration":402,"passed_time":0.4067107628,"remaining_time":0.6024970853},
{"learn":[3.280790082],"iteration":403,"passed_time":0.4076749431,"remaining_time":0.6014214508},
{"learn":[3.276249982],"iteration":404,"passed_time":0.4087605643,"remaining_time":0.6005247797},
{"learn":[3.273177762],"iteration":405,"passed_time":0.4097637526,"remaining_time":0.599506574},
{"learn":[3.26975737],"iteration":406,"passed_time":0.4106684918,"remaining_time":0.5983450016},
{"learn":[3.265666604],"iteration":407,"passed_time":0.4116241476,"remaining_time":0.5972585671},
{"learn":[3.262368456],"iteration":408,"passed_time":0.41253514,"remaining_time":0.596108234},
{"learn":[3.259789254],"iteration":409,"passed_time":0.4134839638,"remaining_time":0.595013509},
{"learn":[3.256228993],"iteration":410,"passed_time":0.4143783701,"remaining_time":0.5938415085},
{"learn":[3.251745078],"iteration":411,"passed_time":0.4152623261,"remaining_time":0.5926559411},
{"learn":[3.249740149],"iteration":412,"passed_time":0.4162096521,"remaining_time":0.5915619026},
{"learn":[3.246254086],"iteration":413,"passed_time":0.4170681064,"remaining_time":0.5903427787},
{"learn":[3.243345235],"iteration":414,"passed_time":0.4179248467,"remaining_time":0.5891229767},
{"learn":[3.239726966],"iteration":415,"passed_time":0.4188761107,"remaining_time":0.5880376169},
{"learn":[3.236158753],"iteration":416,"passed_time":0.4197693494,"remaining_time":0.5868717763},
{"learn":[3.231157635],"iteration":417,"passed_time":0.4206986565,"remaining_time":0.5857574596},
{"learn":[3.227384325],"iteration":418,"passed_time":0.4215718794,"remaining_time":0.5845662576},
{"learn":[3.224718328],"iteration":419,"passed_time":0.4225557023,"remaining_time":0.5835293031},
{"learn":[3.222058313],"iteration":420,"passed_time":0.4235043713,"remaining_time":0.5824442541},
{"learn":[3.219100162],"iteration":421,"passed_time":0.4244895108,"remaining_time":0.5814098039},
{"learn":[3.215921588],"iteration":422,"passed_time":0.4254418887,"remaining_time":0.5803308978},
{"learn":[3.213323096],"iteration":423,"passed_time":0.4264215643,"remaining_time":0.5792896722},
{"learn":[3.211667124],"iteration":424,"passed_time":0.4273564346,"remaining_time":0.5781881173},
{"learn":[3.208240293],"iteration":425,"passed_time":0.4282076178,"remaining_time":0.5769745836},
{"learn":[3.20447412],"iteration":426,"passed_time":0.4291237693,"remaining_time":0.5758499293},
{"learn":[3.202388718],"iteration":427,"passed_time":0.4299934984,"remaining_time":0.5746642082},
{"learn":[3.200926099],"iteration":428,"passed_time":0.4308488075,"remaining_time":0.573460767},
{"learn":[3.197934972],"iteration":429,"passed_time":0.4317352089,"remaining_time":0.5723001606},
{"learn":[3.195785329],"iteration":430,"passed_time":0.4326478042,"remaining_time":0.5711754074},
{"learn":[3.192483267],"iteration":431,"passed_time":0.4335710782,"remaining_time":0.5700656769},
{"learn":[3.188425828],"iteration":432,"passed_time":0.4343890126,"remaining_time":0.5688188686},
{"learn":[3.18509396],"iteration":433,"passed_time":0.4353039375,"remaining_time":0.5677005268},
{"learn":[3.181214373],"iteration":434,"passed_time":0.4361171665,"remaining_time":0.5664510324},
{"learn":[3.177876351],"iteration":435,"passed_time":0.4369674015,"remaining_time":0.5652514093},
{"learn":[3.175736113],"iteration":436,"passed_time":0.4378337572,"remaining_time":0.564074154},
{"learn":[3.172955647],"iteration":437,"passed_time":0.4387220414,"remaining_time":0.5629264549},
{"learn":[3.169432292],"iteration":438,"passed_time":0.4396460881,"remaining_time":0.5618256388},
{"learn":[3.166813894],"iteration":439,"passed_time":0.4406324197,"remaining_time":0.5608048978},
{"learn":[3.162713986],"iteration":440,"passed_time":0.4416530266,"remaining_time":0.5598277593},
{"learn":[3.157555657],"iteration":441,"passed_time":0.4425957901,"remaining_time":0.5587521513},
{"learn":[3.154769229],"iteration":442,"passed_time":0.4435746155,"remaining_time":0.557722485},
{"learn":[3.152516669],"iteration":443,"passed_time":0.4444456268,"remaining_time":0.5565580372},
{"learn":[3.150267587],"iteration":444,"passed_time":0.4453660989,"remaining_time":0.5554565952},
{"learn":[3.146084488],"iteration":445,"passed_time":0.4462616519,"remaining_time":0.5543250116},
{"learn":[3.143123012],"iteration":446,"passed_time":0.4471784145,"remaining_time":0.553220723},
{"learn":[3.139969049],"iteration":447,"passed_time":0.4480957818,"remaining_time":0.5521180169},
{"learn":[3.135526999],"iteration":448,"passed_time":0.4489871186,"remaining_time":0.5509841923},
{"learn":[3.13279032],"iteration":449,"passed_time":0.4499736828,"remaining_time":0.5499678346},
{"learn":[3.130984333],"iteration":450,"passed_time":0.4508941588,"remaining_time":0.54887116},
{"learn":[3.128190962],"iteration":451,"passed_time":0.4519534922,"remaining_time":0.5479436144},
{"learn":[3.124631185],"iteration":452,"passed_time":0.4528971247,"remaining_time":0.5468757775},
{"learn":[3.121753901],"iteration":453,"passed_time":0.4538707074,"remaining_time":0.5458445071},
{"learn":[3.11794001],"iteration":454,"passed_time":0.4547518055,"remaining_time":0.5447027121},
{"learn":[3.115543408],"iteration":455,"passed_time":0.4556341877,"remaining_time":0.5435635923},
{"learn":[3.111000221],"iteration":456,"passed_time":0.4566721265,"remaining_time":0.5426104261},
{"learn":[3.109437684],"iteration":457,"passed_time":0.4577309015,"remaining_time":0.5416815472},
{"learn":[3.106525862],"iteration":458,"passed_time":0.4586341351,"remaining_time":0.5405687737},
{"learn":[3.102130261],"iteration":459,"passed_time":0.4594936681,"remaining_time":0.5394056104},
{"learn":[3.100307456],"iteration":460,"passed_time":0.460386417,"remaining_time":0.5382826003},
{"learn":[3.097979713],"iteration":461,"passed_time":0.4612795852,"remaining_time":0.5371610754},
{"learn":[3.093369711],"iteration":462,"passed_time":0.4621988939,"remaining_time":0.5360708554},
{"learn":[3.092263825],"iteration":463,"passed_time":0.4630847139,"remaining_time":0.5349426868},
{"learn":[3.08901805],"iteration":464,"passed_time":0.4641445077,"remaining_time":0.5340157239},
{"learn":[3.086847455],"iteration":465,"passed_time":0.4650028341,"remaining_time":0.5328573249},
{"learn":[3.085407549],"iteration":466,"passed_time":0.4659247696,"remaining_time":0.5317728098},
{"learn":[3.082743188],"iteration":467,"passed_time":0.466944854,"remaining_time":0.5308005606},
{"learn":[3.080149287],"iteration":468,"passed_time":0.4680183569,"remaining_time":0.5298885874},
{"learn":[3.078704074],"iteration":469,"passed_time":0.4690832198,"remaining_time":0.528966184},
{"learn":[3.074808979],"iteration":470,"passed_time":0.4700312893,"remaining_time":0.5279120001},
{"learn":[3.072723645],"iteration":471,"passed_time":0.4709107692,"remaining_time":0.5267815384},
{"learn":[3.069203701],"iteration":472,"passed_time":0.4719288352,"remaining_time":0.5258065457},
{"learn":[3.067497527],"iteration":473,"passed_time":0.4730502998,"remaining_time":0.5249461132},
{"learn":[3.062510412],"iteration":474,"passed_time":0.4740718695,"remaining_time":0.5239741715},
{"learn":[3.05958306],"iteration":475,"passed_time":0.4749518944,"remaining_time":0.5228462031},
{"learn":[3.057804557],"iteration":476,"passed_time":0.4758490788,"remaining_time":0.5217380885},
{"learn":[3.054543136],"iteration":477,"passed_time":0.4768153542,"remaining_time":0.5207063074},
{"learn":[3.050794715],"iteration":478,"passed_time":0.4777338355,"remaining_time":0.5196228148},
{"learn":[3.047528577],"iteration":479,"passed_time":0.4786685049,"remaining_time":0.518557547},
{"learn":[3.044119712],"iteration":480,"passed_time":0.4795961784,"remaining_time":0.5174852736},
{"learn":[3.042276513],"iteration":481,"passed_time":0.4805111218,"remaining_time":0.5163999193},
{"learn":[3.039687485],"iteration":482,"passed_time":0.4817164026,"remaining_time":0.5156260459},
{"learn":[3.037143321],"iteration":483,"passed_time":0.4827271388,"remaining_time":0.5146429827},
{"learn":[3.034730176],"iteration":484,"passed_time":0.4837003704,"remaining_time":0.5136199809},
{"learn":[3.032984513],"iteration":485,"passed_time":0.4846071495,"remaining_time":0.512526903},
{"learn":[3.028630544],"iteration":486,"passed_time":0.4855782568,"remaining_time":0.5115023527},
{"learn":[3.025521054],"iteration":487,"passed_time":0.4864582227,"remaining_time":0.5103823976},
{"learn":[3.022488535],"iteration":488,"passed_time":0.4874629449,"remaining_time":0.5093937932},
{"learn":[3.020605678],"iteration":489,"passed_time":0.488447631,"remaining_time":0.508384269},
{"learn":[3.017747594],"iteration":490,"passed_time":0.4893992629,"remaining_time":0.5073405801},
{"learn":[3.016226385],"iteration":491,"passed_time":0.4903710058,"remaining_time":0.5063180304},
{"learn":[3.013845541],"iteration":492,"passed_time":0.49129154,"remaining_time":0.5052430239},
{"learn":[3.011262661],"iteration":493,"passed_time":0.4921454592,"remaining_time":0.5041004096},
{"learn":[3.008521339],"iteration":494,"passed_time":0.49302085,"remaining_time":0.5029808671},
{"learn":[3.006098895],"iteration":495,"passed_time":0.4939205979,"remaining_time":0.5018870591},
{"learn":[3.003008159],"iteration":496,"passed_time":0.4947082846,"remaining_time":0.500680618},
{"learn":[2.999554529],"iteration":497,"passed_time":0.4957355502,"remaining_time":0.4997173618},
{"learn":[2.995723488],"iteration":498,"passed_time":0.4968076141,"remaining_time":0.498798827},
{"learn":[2.991869397],"iteration":499,"passed_time":0.4977978791,"remaining_time":0.4977978791},
{"learn":[2.98729073],"iteration":500,"passed_time":0.498904528,"remaining_time":0.4969128932},
{"learn":[2.985560349],"iteration":501,"passed_time":0.5001755791,"remaining_time":0.4961901163},
{"learn":[2.983745157],"iteration":502,"passed_time":0.5011708376,"remaining_time":0.4951926567},
{"learn":[2.982823825],"iteration":503,"passed_time":0.5023131268,"remaining_time":0.4943399026},
{"learn":[2.981099383],"iteration":504,"passed_time":0.5037712225,"remaining_time":0.4937955548},
{"learn":[2.977078384],"iteration":505,"passed_time":0.5046837695,"remaining_time":0.4927149845},
{"learn":[2.974838307],"iteration":506,"passed_time":0.5056357372,"remaining_time":0.4916734092},
{"learn":[2.971590319],"iteration":507,"passed_time":0.5065569031,"remaining_time":0.490602355},
{"learn":[2.96991915],"iteration":508,"passed_time":0.5075733577,"remaining_time":0.4896238087},
{"learn":[2.966012117],"iteration":509,"passed_time":0.5085499255,"remaining_time":0.4886067912},
{"learn":[2.96103585],"iteration":510,"passed_time":0.50949341,"remaining_time":0.487558273},
{"learn":[2.958607031],"iteration":511,"passed_time":0.5104160052,"remaining_time":0.486490255},
{"learn":[2.954854102],"iteration":512,"passed_time":0.5114821353,"remaining_time":0.4855590641},
{"learn":[2.952903187],"iteration":513,"passed_time":0.512517582,"remaining_time":0.4845983363},
{"learn":[2.949909524],"iteration":514,"passed_time":0.513502117,"remaining_time":0.4835893723},
{"learn":[2.946874092],"iteration":515,"passed_time":0.5143775071,"remaining_time":0.4824781268},
{"learn":[2.944427174],"iteration":516,"passed_time":0.5153320563,"remaining_time":0.481441747},
{"learn":[2.942776561],"iteration":517,"passed_time":0.5162533141,"remaining_time":0.4803747054},
{"learn":[2.939562655],"iteration":518,"passed_time":0.5172110294,"remaining_time":0.4793420138},
{"learn":[2.936666746],"iteration":519,"passed_time":0.518128496,"remaining_time":0.4782724579},
{"learn":[2.934706677],"iteration":520,"passed_time":0.5192306734,"remaining_time":0.4773733063},
{"learn":[2.931747316],"iteration":521,"passed_time":0.5202469893,"remaining_time":0.4763947526},
{"learn":[2.929547556],"iteration":522,"passed_time":0.5211436654,"remaining_time":0.4753069377},
{"learn":[2.927679802],"iteration":523,"passed_time":0.5219981274,"remaining_time":0.474181505},
{"learn":[2.925749902],"iteration":524,"passed_time":0.5229311034,"remaining_time":0.4731281412},
{"learn":[2.922807938],"iteration":525,"passed_time":0.5238312177,"remaining_time":0.4720456221},
{"learn":[2.920406318],"iteration":526,"passed_time":0.5246741876,"remaining_time":0.4709125062},
{"learn":[2.91915301],"iteration":527,"passed_time":0.5255681929,"remaining_time":0.4698261119},
{"learn":[2.916593163],"iteration":528,"passed_time":0.5264106584,"remaining_time":0.468694556},
{"learn":[2.913139325],"iteration":529,"passed_time":0.5272491476,"remaining_time":0.4675605648},
{"learn":[2.910715142],"iteration":530,"passed_time":0.5281174734,"remaining_time":0.4664540396},
{"learn":[2.907905479],"iteration":531,"passed_time":0.5291734894,"remaining_time":0.4655135208},
{"learn":[2.905631607],"iteration":532,"passed_time":0.5301050219,"remaining_time":0.4644634995},
{"learn":[2.902035441],"iteration":533,"passed_time":0.5311273525,"remaining_time":0.4634931578},
{"learn":[2.898974737],"iteration":534,"passed_time":0.5320657913,"remaining_time":0.4624497065},
{"learn":[2.895213085],"iteration":535,"passed_time":0.5329451155,"remaining_time":0.4613554732},
{"learn":[2.892200285],"iteration":536,"passed_time":0.5339170907,"remaining_time":0.4603419236},
{"learn":[2.889960453],"iteration":537,"passed_time":0.5350589172,"remaining_time":0.4594743862},
{"learn":[2.886557733],"iteration":538,"passed_time":0.5361232937,"remaining_time":0.4585395889},
{"learn":[2.884733651],"iteration":539,"passed_time":0.5371280064,"remaining_time":0.4575534869},
{"learn":[2.881635348],"iteration":540,"passed_time":0.5380013925,"remaining_time":0.456455895},
{"learn":[2.878047493],"iteration":541,"passed_time":0.5389510183,"remaining_time":0.4554235542},
{"learn":[2.874841843],"iteration":542,"passed_time":0.539818842,"remaining_time":0.4543226718},
{"learn":[2.871889969],"iteration":543,"passed_time":0.540857618,"remaining_time":0.4533659445},
{"learn":[2.869902372],"iteration":544,"passed_time":0.5417387215,"remaining_time":0.4522772813},
{"learn":[2.867440823],"iteration":545,"passed_time":0.5427049981,"remaining_time":0.4512601999},
{"learn":[2.865804496],"iteration":546,"passed_time":0.5435986493,"remaining_time":0.4501831593},
{"learn":[2.861732842],"iteration":547,"passed_time":0.5445312727,"remaining_time":0.4491389329},
{"learn":[2.860289445],"iteration":548,"passed_time":0.5454101822,"remaining_time":0.4480509875},
{"learn":[2.857808292],"iteration":549,"passed_time":0.5463520983,"remaining_time":0.4470153531},
{"learn":[2.854868815],"iteration":550,"passed_time":0.5472606214,"remaining_time":0.4459528476},
{"learn":[2.851692838],"iteration":551,"passed_time":0.5481669912,"remaining_time":0.4448891522},
{"learn":[2.849222447],"iteration":552,"passed_time":0.5491711729,"remaining_time":0.4439050892},
{"learn":[2.846969],"iteration":553,"passed_time":0.5500638336,"remaining_time":0.4428311729},
{"learn":[2.845474225],"iteration":554,"passed_time":0.5510008259,"remaining_time":0.441793455},
{"learn":[2.842937105],"iteration":555,"passed_time":0.5519499879,"remaining_time":0.4407658176},
{"learn":[2.840020955],"iteration":556,"passed_time":0.5528745129,"remaining_time":0.4397188676},
{"learn":[2.838535917],"iteration":557,"passed_time":0.553824709,"remaining_time":0.4386926907},
{"learn":[2.836518579],"iteration":558,"passed_time":0.5548336134,"remaining_time":0.4377131011},
{"learn":[2.834483427],"iteration":559,"passed_time":0.5557355124,"remaining_time":0.4366493312},
{"learn":[2.830736948],"iteration":560,"passed_time":0.5567716179,"remaining_time":0.4356911591},
{"learn":[2.827856278],"iteration":561,"passed_time":0.5577725988,"remaining_time":0.434705335},
{"learn":[2.825141906],"iteration":562,"passed_time":0.5586402163,"remaining_time":0.4336159406},
{"learn":[2.823341218],"iteration":563,"passed_time":0.5595455926,"remaining_time":0.4325565219},
{"learn":[2.819733128],"iteration":564,"passed_time":0.56050121,"remaining_time":0.4315363299},
{"learn":[2.818366639],"iteration":565,"passed_time":0.5614342528,"remaining_time":0.430499056},
{"learn":[2.817003607],"iteration":566,"passed_time":0.5623266697,"remaining_time":0.4294311252},
{"learn":[2.813345212],"iteration":567,"passed_time":0.5633144551,"remaining_time":0.4284363462},
{"learn":[2.809811151],"iteration":568,"passed_time":0.5641858152,"remaining_time":0.4273534031},
{"learn":[2.805155501],"iteration":569,"passed_time":0.5651064651,"remaining_time":0.426308386},
{"learn":[2.802062058],"iteration":570,"passed_time":0.566123431,"remaining_time":0.425336168},
{"learn":[2.799304034],"iteration":571,"passed_time":0.5670986569,"remaining_time":0.4243325615},
{"learn":[2.796996541],"iteration":572,"passed_time":0.5679912034,"remaining_time":0.4232674413},
{"learn":[2.793860999],"iteration":573,"passed_time":0.5688997005,"remaining_time":0.4222147603},
{"learn":[2.791415147],"iteration":574,"passed_time":0.5699096578,"remaining_time":0.4212375731},
{"learn":[2.788788611],"iteration":575,"passed_time":0.5708004771,"remaining_time":0.4201725734},
{"learn":[2.785388816],"iteration":576,"passed_time":0.5717125335,"remaining_time":0.4191237464},
{"learn":[2.784098693],"iteration":577,"passed_time":0.5725762383,"remaining_time":0.4180400909},
{"learn":[2.78206603],"iteration":578,"passed_time":0.5734363248,"remaining_time":0.4169545643},
{"learn":[2.778881595],"iteration":579,"passed_time":0.5742968559,"remaining_time":0.415870137},
{"learn":[2.777637633],"iteration":580,"passed_time":0.575202423,"remaining_time":0.4148189591},
{"learn":[2.774820768],"iteration":581,"passed_time":0.5762155115,"remaining_time":0.4138455048},
{"learn":[2.77258508],"iteration":582,"passed_time":0.5770472906,"remaining_time":0.4127422302},
{"learn":[2.772247817],"iteration":583,"passed_time":0.5779205625,"remaining_time":0.4116694418},
{"learn":[2.76899524],"iteration":584,"passed_time":0.578804517,"remaining_time":0.4106049138},
{"learn":[2.767116286],"iteration":585,"passed_time":0.5797269531,"remaining_time":0.4095681887},
{"learn":[2.7633462],"iteration":586,"passed_time":0.5806776007,"remaining_time":0.408551702},
{"learn":[2.760336924],"iteration":587,"passed_time":0.5815381303,"remaining_time":0.4074722954},
{"learn":[2.757413877],"iteration":588,"passed_time":0.5825005559,"remaining_time":0.4064647343},
{"learn":[2.756087847],"iteration":589,"passed_time":0.5833863878,"remaining_time":0.4054041},
{"learn":[2.75358756],"iteration":590,"passed_time":0.5842984606,"remaining_time":0.4043622173},
{"learn":[2.751970654],"iteration":591,"passed_time":0.5854198543,"remaining_time":0.4034650347},
{"learn":[2.750078693],"iteration":592,"passed_time":0.5863228158,"remaining_time":0.4024171771},
{"learn":[2.748759543],"iteration":593,"passed_time":0.587217741,"remaining_time":0.4013643146},
{"learn":[2.74694072],"iteration":594,"passed_time":0.5881179757,"remaining_time":0.4003155969},
{"learn":[2.744237429],"iteration":595,"passed_time":0.5890651943,"remaining_time":0.3992992257},
{"learn":[2.741787155],"iteration":596,"passed_time":0.5900413175,"remaining_time":0.3983025979},
{"learn":[2.737431673],"iteration":597,"passed_time":0.5910271412,"remaining_time":0.3973125598},
{"learn":[2.735667394],"iteration":598,"passed_time":0.592037969,"remaining_time":0.3963392747},
{"learn":[2.734241517],"iteration":599,"passed_time":0.5929064145,"remaining_time":0.395270943},
{"learn":[2.732355991],"iteration":600,"passed_time":0.5937840092,"remaining_time":0.3942093506},
{"learn":[2.729154418],"iteration":601,"passed_time":0.5946753062,"remaining_time":0.3931574283},
{"learn":[2.727117629],"iteration":602,"passed_time":0.5955525054,"remaining_time":0.3920967573},
{"learn":[2.725378457],"iteration":603,"passed_time":0.5964348002,"remaining_time":0.3910400345},
{"learn":[2.723318841],"iteration":604,"passed_time":0.5973051299,"remaining_time":0.3899760765},
{"learn":[2.722190466],"iteration":605,"passed_time":0.5983098287,"remaining_time":0.3890001197},
{"learn":[2.719634488],"iteration":606,"passed_time":0.5993946301,"remaining_time":0.3880759302},
{"learn":[2.718204568],"iteration":607,"passed_time":0.6003359145,"remaining_time":0.3870586817},
{"learn":[2.71655444],"iteration":608,"passed_time":0.6011806154,"remaining_time":0.3859796726},
{"learn":[2.71511118],"iteration":609,"passed_time":0.6020566087,"remaining_time":0.3849214384},
{"learn":[2.713477797],"iteration":610,"passed_time":0.6029453,"remaining_time":0.3838718849},
{"learn":[2.711244651],"iteration":611,"passed_time":0.6038516345,"remaining_time":0.3828340428},
{"learn":[2.709083834],"iteration":612,"passed_time":0.6048928586,"remaining_time":0.3818817884},
{"learn":[2.707493529],"iteration":613,"passed_time":0.6057451511,"remaining_time":0.3808104696},
{"learn":[2.704208868],"iteration":614,"passed_time":0.6066451052,"remaining_time":0.3797697},
{"learn":[2.702910127],"iteration":615,"passed_time":0.6074973394,"remaining_time":0.3786996402},
{"learn":[2.701771582],"iteration":616,"passed_time":0.6083823219,"remaining_time":0.3776506147},
{"learn":[2.699049376],"iteration":617,"passed_time":0.6092107901,"remaining_time":0.3765671874},
{"learn":[2.696852622],"iteration":618,"passed_time":0.6100995887,"remaining_time":0.3755217177},
{"learn":[2.695340534],"iteration":619,"passed_time":0.6110930707,"remaining_time":0.3745409143},
{"learn":[2.693279068],"iteration":620,"passed_time":0.6121480544,"remaining_time":0.3735976049},
{"learn":[2.690907697],"iteration":621,"passed_time":0.6130520385,"remaining_time":0.3725621713},
{"learn":[2.688421507],"iteration":622,"passed_time":0.6141082148,"remaining_time":0.3716192568},
{"learn":[2.68320485],"iteration":623,"passed_time":0.6149984208,"remaining_time":0.3705759715},
{"learn":[2.681001395],"iteration":624,"passed_time":0.6160730582,"remaining_time":0.3696438349},
{"learn":[2.678833723],"iteration":625,"passed_time":0.6169844323,"remaining_time":0.3686137024},
{"learn":[2.677662234],"iteration":626,"passed_time":0.6178877736,"remaining_time":0.36757917},
{"learn":[2.674425083],"iteration":627,"passed_time":0.6188864198,"remaining_time":0.3666015098},
{"learn":[2.673796249],"iteration":628,"passed_time":0.6198638263,"remaining_time":0.3656112552},
{"learn":[2.671966844],"iteration":629,"passed_time":0.6206942294,"remaining_time":0.3645347061},
{"learn":[2.670082628],"iteration":630,"passed_time":0.6216283001,"remaining_time":0.3635195606},
{"learn":[2.667796459],"iteration":631,"passed_time":0.6225054326,"remaining_time":0.3624715177},
{"learn":[2.665170838],"iteration":632,"passed_time":0.6234964262,"remaining_time":0.3614900291},
{"learn":[2.663284958],"iteration":633,"passed_time":0.624381756,"remaining_time":0.3604475121},
{"learn":[2.661539029],"iteration":634,"passed_time":0.6252112775,"remaining_time":0.3593734115},
{"learn":[2.660090494],"iteration":635,"passed_time":0.626093744,"remaining_time":0.3583303818},
{"learn":[2.656431986],"iteration":636,"passed_time":0.6270185343,"remaining_time":0.3573119748},
{"learn":[2.654811722],"iteration":637,"passed_time":0.6279007884,"remaining_time":0.3562697264},
{"learn":[2.651807395],"iteration":638,"passed_time":0.628848643,"remaining_time":0.3552650393},
{"learn":[2.649584422],"iteration":639,"passed_time":0.6298494686,"remaining_time":0.3542903261},
{"learn":[2.648653119],"iteration":640,"passed_time":0.6307964925,"remaining_time":0.3532853991},
{"learn":[2.645735696],"iteration":641,"passed_time":0.6316984152,"remaining_time":0.3522555026},
{"learn":[2.643774019],"iteration":642,"passed_time":0.6326626278,"remaining_time":0.3512605881},
{"learn":[2.642301849],"iteration":643,"passed_time":0.6334823652,"remaining_time":0.3501859038},
{"learn":[2.640019736],"iteration":644,"passed_time":0.6344456548,"remaining_time":0.3491910193},
{"learn":[2.638763942],"iteration":645,"passed_time":0.6353207681,"remaining_time":0.3481479132},
{"learn":[2.63613236],"iteration":646,"passed_time":0.6362732119,"remaining_time":0.3471475174},
{"learn":[2.634569873],"iteration":647,"passed_time":0.6371395645,"remaining_time":0.3461005042},
{"learn":[2.630283286],"iteration":648,"passed_time":0.638053545,"remaining_time":0.3450798063},
{"learn":[2.628162821],"iteration":649,"passed_time":0.6389437764,"remaining_time":0.3440466488},
{"learn":[2.625055815],"iteration":650,"passed_time":0.6398964425,"remaining_time":0.3430474016},
{"learn":[2.62313838],"iteration":651,"passed_time":0.640806498,"remaining_time":0.3420255542},
{"learn":[2.621354468],"iteration":652,"passed_time":0.6417636928,"remaining_time":0.3410290986},
{"learn":[2.618551045],"iteration":653,"passed_time":0.6427520949,"remaining_time":0.3400492735},
{"learn":[2.615842513],"iteration":654,"passed_time":0.6440263775,"remaining_time":0.3392200004},
{"learn":[2.614512417],"iteration":655,"passed_time":0.6451249385,"remaining_time":0.3382972239},
{"learn":[2.61322553],"iteration":656,"passed_time":0.6461781848,"remaining_time":0.3373502548},
{"learn":[2.610974147],"iteration":657,"passed_time":0.6473247183,"remaining_time":0.3364514493},
{"learn":[2.608569712],"iteration":658,"passed_time":0.6484829557,"remaining_time":0.3355579483},
{"learn":[2.605579778],"iteration":659,"passed_time":0.649571196,"remaining_time":0.3346275858},
{"learn":[2.603331493],"iteration":660,"passed_time":0.6507773128,"remaining_time":0.3337571998},
{"learn":[2.599004318],"iteration":661,"passed_time":0.6517500384,"remaining_time":0.3327666359},
{"learn":[2.5973084],"iteration":662,"passed_time":0.6525966205,"remaining_time":0.3317120077},
{"learn":[2.595369594],"iteration":663,"passed_time":0.6535538444,"remaining_time":0.3307139936},
{"learn":[2.593419217],"iteration":664,"passed_time":0.654715077,"remaining_time":0.3298188734},
{"learn":[2.592386753],"iteration":665,"passed_time":0.6557509062,"remaining_time":0.3288600641},
{"learn":[2.59057484],"iteration":666,"passed_time":0.6566872779,"remaining_time":0.3278513696},
{"learn":[2.586742686],"iteration":667,"passed_time":0.6577545448,"remaining_time":0.3269079474},
{"learn":[2.583509833],"iteration":668,"passed_time":0.6588697988,"remaining_time":0.3259878975},
{"learn":[2.581610925],"iteration":669,"passed_time":0.6598748231,"remaining_time":0.3250129726},
{"learn":[2.580282219],"iteration":670,"passed_time":0.6608838045,"remaining_time":0.3240398982},
{"learn":[2.577464574],"iteration":671,"passed_time":0.66215402,"remaining_time":0.323194224},
{"learn":[2.57537376],"iteration":672,"passed_time":0.6633661983,"remaining_time":0.3223190889},
{"learn":[2.572146639],"iteration":673,"passed_time":0.664359484,"remaining_time":0.3213370798},
{"learn":[2.570795517],"iteration":674,"passed_time":0.6653943883,"remaining_time":0.3203750759},
{"learn":[2.56859784],"iteration":675,"passed_time":0.6665074771,"remaining_time":0.3194503292},
{"learn":[2.566679892],"iteration":676,"passed_time":0.6677064193,"remaining_time":0.3185659874},
{"learn":[2.564689974],"iteration":677,"passed_time":0.6689535253,"remaining_time":0.3177035917},
{"learn":[2.562507071],"iteration":678,"passed_time":0.6700383193,"remaining_time":0.3167633292},
{"learn":[2.560040283],"iteration":679,"passed_time":0.6710546068,"remaining_time":0.3157904032},
{"learn":[2.558735575],"iteration":680,"passed_time":0.6721123825,"remaining_time":0.3148367842},
{"learn":[2.557157783],"iteration":681,"passed_time":0.6732322833,"remaining_time":0.3139118271},
{"learn":[2.554008909],"iteration":682,"passed_time":0.674277437,"remaining_time":0.3129516069},
{"learn":[2.551212633],"iteration":683,"passed_time":0.6753789294,"remaining_time":0.3120171662},
{"learn":[2.547540596],"iteration":684,"passed_time":0.6765126155,"remaining_time":0.3110970422},
{"learn":[2.545040071],"iteration":685,"passed_time":0.6775148336,"remaining_time":0.3101161192},
{"learn":[2.543067789],"iteration":686,"passed_time":0.6786142639,"remaining_time":0.3091794245},
{"learn":[2.541385318],"iteration":687,"passed_time":0.6797921987,"remaining_time":0.3082778575},
{"learn":[2.539619968],"iteration":688,"passed_time":0.6809232986,"remaining_time":0.3073543482},
{"learn":[2.537630519],"iteration":689,"passed_time":0.6819316672,"remaining_time":0.3063750969},
{"learn":[2.5354433],"iteration":690,"passed_time":0.6828572433,"remaining_time":0.3053587383},
{"learn":[2.533296324],"iteration":691,"passed_time":0.6839062656,"remaining_time":0.3043975864},
{"learn":[2.530422924],"iteration":692,"passed_time":0.6851131459,"remaining_time":0.3035061123},
{"learn":[2.528837576],"iteration":693,"passed_time":0.6860541046,"remaining_time":0.3024964784},
{"learn":[2.526183798],"iteration":694,"passed_time":0.6872506117,"remaining_time":0.3015991893},
{"learn":[2.523599089],"iteration":695,"passed_time":0.6884048065,"remaining_time":0.3006825592},
{"learn":[2.521674024],"iteration":696,"passed_time":0.6896003853,"remaining_time":0.2997832378},
{"learn":[2.520656458],"iteration":697,"passed_time":0.6907144626,"remaining_time":0.2988478047},
{"learn":[2.518882924],"iteration":698,"passed_time":0.6917744013,"remaining_time":0.2978885476},
{"learn":[2.516569431],"iteration":699,"passed_time":0.6927181948,"remaining_time":0.2968792263},
{"learn":[2.513019266],"iteration":700,"passed_time":0.6937071339,"remaining_time":0.2958893481},
{"learn":[2.510351572],"iteration":701,"passed_time":0.6950851164,"remaining_time":0.2950646221},
{"learn":[2.508094775],"iteration":702,"passed_time":0.6961480475,"remaining_time":0.2941052206},
{"learn":[2.506940288],"iteration":703,"passed_time":0.6971380694,"remaining_time":0.2931148701},
{"learn":[2.505457631],"iteration":704,"passed_time":0.6982039761,"remaining_time":0.2921562737},
{"learn":[2.503661716],"iteration":705,"passed_time":0.6994515903,"remaining_time":0.2912730418},
{"learn":[2.501583543],"iteration":706,"passed_time":0.7004877794,"remaining_time":0.2903011589},
{"learn":[2.498971927],"iteration":707,"passed_time":0.7014222196,"remaining_time":0.2892871301},
{"learn":[2.497389098],"iteration":708,"passed_time":0.7025744006,"remaining_time":0.2883626948},
{"learn":[2.494164856],"iteration":709,"passed_time":0.7036183998,"remaining_time":0.2873934309},
{"learn":[2.49274667],"iteration":710,"passed_time":0.7046410152,"remaining_time":0.286415265},
{"learn":[2.490348435],"iteration":711,"passed_time":0.7059431007,"remaining_time":0.2855500183},
{"learn":[2.486400085],"iteration":712,"passed_time":0.7070365201,"remaining_time":0.284599553},
{"learn":[2.484022663],"iteration":713,"passed_time":0.7080688276,"remaining_time":0.2836242083},
{"learn":[2.48248108],"iteration":714,"passed_time":0.7091695791,"remaining_time":0.2826759861},
{"learn":[2.480678472],"iteration":715,"passed_time":0.7102408734,"remaining_time":0.2817156537},
{"learn":[2.480100101],"iteration":716,"passed_time":0.7113315016,"remaining_time":0.2807626429},
{"learn":[2.47859906],"iteration":717,"passed_time":0.7122076889,"remaining_time":0.2797250255},
{"learn":[2.476248921],"iteration":718,"passed_time":0.7131898801,"remaining_time":0.2787292855},
{"learn":[2.474945388],"iteration":719,"passed_time":0.7143364611,"remaining_time":0.2777975126},
{"learn":[2.47144276],"iteration":720,"passed_time":0.7153819141,"remaining_time":0.2768260112},
{"learn":[2.471020604],"iteration":721,"passed_time":0.7163244435,"remaining_time":0.2758146749},
{"learn":[2.469477411],"iteration":722,"passed_time":0.7174676503,"remaining_time":0.2748804137},
{"learn":[2.468168505],"iteration":723,"passed_time":0.7185755377,"remaining_time":0.2739321111},
{"learn":[2.466884117],"iteration":724,"passed_time":0.7196829916,"remaining_time":0.2729832037},
{"learn":[2.465475631],"iteration":725,"passed_time":0.7206997084,"remaining_time":0.2719996145},
{"learn":[2.46382149],"iteration":726,"passed_time":0.7217662984,"remaining_time":0.2710346623},
{"learn":[2.462430325],"iteration":727,"passed_time":0.7228897596,"remaining_time":0.2700906794},
{"learn":[2.460777457],"iteration":728,"passed_time":0.7238828342,"remaining_time":0.269097734},
{"learn":[2.458962329],"iteration":729,"passed_time":0.7249845585,"remaining_time":0.2681449737},
{"learn":[2.456844784],"iteration":730,"passed_time":0.7260326785,"remaining_time":0.2671720801},
{"learn":[2.455373591],"iteration":731,"passed_time":0.7270063459,"remaining_time":0.2661717223},
{"learn":[2.454162263],"iteration":732,"passed_time":0.727910171,"remaining_time":0.2651459968},
{"learn":[2.452100645],"iteration":733,"passed_time":0.7289783195,"remaining_time":0.2641801539},
{"learn":[2.450804291],"iteration":734,"passed_time":0.7299981629,"remaining_time":0.2631966165},
{"learn":[2.449493206],"iteration":735,"passed_time":0.7308988334,"remaining_time":0.2621702337},
{"learn":[2.446035488],"iteration":736,"passed_time":0.731991439,"remaining_time":0.2612126845},
{"learn":[2.444057762],"iteration":737,"passed_time":0.7331293617,"remaining_time":0.2602708574},
{"learn":[2.442587496],"iteration":738,"passed_time":0.7342644886,"remaining_time":0.2593275122},
{"learn":[2.439474755],"iteration":739,"passed_time":0.7354689503,"remaining_time":0.2584080096},
{"learn":[2.438367862],"iteration":740,"passed_time":0.7364523657,"remaining_time":0.257410476},
{"learn":[2.434874846],"iteration":741,"passed_time":0.7375751412,"remaining_time":0.2564614372},
{"learn":[2.43368173],"iteration":742,"passed_time":0.7386086369,"remaining_time":0.2554810494},
{"learn":[2.432120899],"iteration":743,"passed_time":0.7396290916,"remaining_time":0.2544960315},
{"learn":[2.430572205],"iteration":744,"passed_time":0.740814462,"remaining_time":0.2535673662},
{"learn":[2.428866381],"iteration":745,"passed_time":0.7418862423,"remaining_time":0.2525993372},
{"learn":[2.426580791],"iteration":746,"passed_time":0.7428877034,"remaining_time":0.2516072141},
{"learn":[2.425113937],"iteration":747,"passed_time":0.7440568239,"remaining_time":0.2506715503},
{"learn":[2.424115271],"iteration":748,"passed_time":0.7451156368,"remaining_time":0.2496982975},
{"learn":[2.42268587],"iteration":749,"passed_time":0.7459943397,"remaining_time":0.2486647799},
{"learn":[2.421246636],"iteration":750,"passed_time":0.7469816663,"remaining_time":0.2476676896},
{"learn":[2.419977181],"iteration":751,"passed_time":0.7480585172,"remaining_time":0.2467001493},
{"learn":[2.416191477],"iteration":752,"passed_time":0.7491780508,"remaining_time":0.2457463194},
{"learn":[2.414574914],"iteration":753,"passed_time":0.7500658125,"remaining_time":0.2447164322},
{"learn":[2.413077184],"iteration":754,"passed_time":0.7511445236,"remaining_time":0.2437488852},
{"learn":[2.410381903],"iteration":755,"passed_time":0.7523621107,"remaining_time":0.2428258664},
{"learn":[2.408817045],"iteration":756,"passed_time":0.7533231905,"remaining_time":0.2418197296},
{"learn":[2.405990026],"iteration":757,"passed_time":0.7542806701,"remaining_time":0.2408125622},
{"learn":[2.404335535],"iteration":758,"passed_time":0.7555808134,"remaining_time":0.2399143294},
{"learn":[2.403324614],"iteration":759,"passed_time":0.7566107851,"remaining_time":0.2389297216},
{"learn":[2.402024849],"iteration":760,"passed_time":0.7575951411,"remaining_time":0.2379306685},
{"learn":[2.400686354],"iteration":761,"passed_time":0.7585541838,"remaining_time":0.2369237477},
{"learn":[2.399054523],"iteration":762,"passed_time":0.7594808231,"remaining_time":0.2359068874},
{"learn":[2.398237568],"iteration":763,"passed_time":0.7603669095,"remaining_time":0.2348777364},
{"learn":[2.396391128],"iteration":764,"passed_time":0.7613814955,"remaining_time":0.2338884333},
{"learn":[2.395051946],"iteration":765,"passed_time":0.7625674474,"remaining_time":0.2329514134},
{"learn":[2.394082812],"iteration":766,"passed_time":0.7636892799,"remaining_time":0.2319942663},
{"learn":[2.392862027],"iteration":767,"passed_time":0.7646191903,"remaining_time":0.2309787137},
{"learn":[2.391473267],"iteration":768,"passed_time":0.7656724006,"remaining_time":0.230000422},
{"learn":[2.390113505],"iteration":769,"passed_time":0.7668982377,"remaining_time":0.2290734996},
{"learn":[2.387169028],"iteration":770,"passed_time":0.7678532216,"remaining_time":0.2280653538},
{"learn":[2.386063418],"iteration":771,"passed_time":0.7687219568,"remaining_time":0.2270318733},
{"learn":[2.384670204],"iteration":772,"passed_time":0.7698180954,"remaining_time":0.2260655985},
{"learn":[2.383165063],"iteration":773,"passed_time":0.7708133451,"remaining_time":0.2250695297},
{"learn":[2.380170421],"iteration":774,"passed_time":0.771753009,"remaining_time":0.2240573252},
{"learn":[2.378524072],"iteration":775,"passed_time":0.7727069821,"remaining_time":0.2230494381},
{"learn":[2.377506753],"iteration":776,"passed_time":0.7738055323,"remaining_time":0.2220831837},
{"learn":[2.375947859],"iteration":777,"passed_time":0.7749195383,"remaining_time":0.2211209994},
{"learn":[2.373735895],"iteration":778,"passed_time":0.7759440368,"remaining_time":0.2201330323},
{"learn":[2.371106867],"iteration":779,"passed_time":0.7769660972,"remaining_time":0.2191442838},
{"learn":[2.369992736],"iteration":780,"passed_time":0.7779236446,"remaining_time":0.21813736},
{"learn":[2.36757915],"iteration":781,"passed_time":0.7789730456,"remaining_time":0.2171561687},
{"learn":[2.366264127],"iteration":782,"passed_time":0.7798497411,"remaining_time":0.2161269398},
{"learn":[2.364060903],"iteration":783,"passed_time":0.7810508138,"remaining_time":0.2151874691},
{"learn":[2.362391772],"iteration":784,"passed_time":0.782055393,"remaining_time":0.2141935153},
{"learn":[2.360548836],"iteration":785,"passed_time":0.7829549493,"remaining_time":0.2131709404},
{"learn":[2.359647061],"iteration":786,"passed_time":0.7839539117,"remaining_time":0.2121755822},
{"learn":[2.358076488],"iteration":787,"passed_time":0.7851956979,"remaining_time":0.2112455431},
{"learn":[2.356664581],"iteration":788,"passed_time":0.7862744848,"remaining_time":0.2102711233},
{"learn":[2.354214614],"iteration":789,"passed_time":0.7872603886,"remaining_time":0.2092717489},
{"learn":[2.353184335],"iteration":790,"passed_time":0.788364266,"remaining_time":0.2083035798},
{"learn":[2.351650518],"iteration":791,"passed_time":0.789479139,"remaining_time":0.2073379557},
{"learn":[2.350488248],"iteration":792,"passed_time":0.7905532804,"remaining_time":0.2063613229},
{"learn":[2.349482292],"iteration":793,"passed_time":0.7915888823,"remaining_time":0.2053744455},
{"learn":[2.348308278],"iteration":794,"passed_time":0.7924950788,"remaining_time":0.2043540769},
{"learn":[2.347427529],"iteration":795,"passed_time":0.7933844684,"remaining_time":0.2033296879},
{"learn":[2.346223818],"iteration":796,"passed_time":0.7942286143,"remaining_time":0.2022941138},
{"learn":[2.344251961],"iteration":797,"passed_time":0.7950647193,"remaining_time":0.2012569841},
{"learn":[2.342948726],"iteration":798,"passed_time":0.7961554108,"remaining_time":0.2002844025},
{"learn":[2.341425126],"iteration":799,"passed_time":0.7972355681,"remaining_time":0.199308892},
{"learn":[2.339411782],"iteration":800,"passed_time":0.7981232658,"remaining_time":0.1982853057},
{"learn":[2.337588569],"iteration":801,"passed_time":0.7991533275,"remaining_time":0.1972972055},
{"learn":[2.33624888],"iteration":802,"passed_time":0.8001689201,"remaining_time":0.1963054511},
{"learn":[2.333308682],"iteration":803,"passed_time":0.8012514174,"remaining_time":0.1953299475},
{"learn":[2.331832467],"iteration":804,"passed_time":0.8021745902,"remaining_time":0.194315584},
{"learn":[2.329697069],"iteration":805,"passed_time":0.8030993353,"remaining_time":0.1933018251},
{"learn":[2.327436272],"iteration":806,"passed_time":0.8040181446,"remaining_time":0.1922868673},
{"learn":[2.326248072],"iteration":807,"passed_time":0.8050711866,"remaining_time":0.1913040443},
{"learn":[2.323429166],"iteration":808,"passed_time":0.8061494339,"remaining_time":0.1903269986},
{"learn":[2.321603735],"iteration":809,"passed_time":0.8073358875,"remaining_time":0.1893750847},
{"learn":[2.319521551],"iteration":810,"passed_time":0.8084550891,"remaining_time":0.1884069197},
{"learn":[2.31742573],"iteration":811,"passed_time":0.8094725211,"remaining_time":0.1874148202},
{"learn":[2.316012345],"iteration":812,"passed_time":0.8104600091,"remaining_time":0.1864157709},
{"learn":[2.314860466],"iteration":813,"passed_time":0.8113544292,"remaining_time":0.1853954838},
{"learn":[2.313591395],"iteration":814,"passed_time":0.8122689923,"remaining_time":0.184380078},
{"learn":[2.312116929],"iteration":815,"passed_time":0.8131946021,"remaining_time":0.1833674103},
{"learn":[2.311059836],"iteration":816,"passed_time":0.8141257835,"remaining_time":0.1823562037},
{"learn":[2.30991978],"iteration":817,"passed_time":0.8151283145,"remaining_time":0.1813610675},
{"learn":[2.307897807],"iteration":818,"passed_time":0.8161333391,"remaining_time":0.1803664644},
{"learn":[2.306465076],"iteration":819,"passed_time":0.8171508899,"remaining_time":0.1793745856},
{"learn":[2.303973546],"iteration":820,"passed_time":0.8181017902,"remaining_time":0.1783681126},
{"learn":[2.302595706],"iteration":821,"passed_time":0.8190265502,"remaining_time":0.1773561143},
{"learn":[2.300744633],"iteration":822,"passed_time":0.8201799781,"remaining_time":0.1763935068},
{"learn":[2.299381942],"iteration":823,"passed_time":0.8210384424,"remaining_time":0.1753674343},
{"learn":[2.297782204],"iteration":824,"passed_time":0.8219992528,"remaining_time":0.1743634779},
{"learn":[2.294661916],"iteration":825,"passed_time":0.8229531098,"remaining_time":0.1733581611},
{"learn":[2.293885217],"iteration":826,"passed_time":0.8238486897,"remaining_time":0.1723407779},
{"learn":[2.292718417],"iteration":827,"passed_time":0.8247679007,"remaining_time":0.1713285977},
{"learn":[2.290969959],"iteration":828,"passed_time":0.8257396566,"remaining_time":0.1703274804},
{"learn":[2.288051709],"iteration":829,"passed_time":0.8267170807,"remaining_time":0.1693275948},
{"learn":[2.286441404],"iteration":830,"passed_time":0.8276250933,"remaining_time":0.1683136471},
{"learn":[2.283255101],"iteration":831,"passed_time":0.8285297052,"remaining_time":0.1672992674},
{"learn":[2.281939505],"iteration":832,"passed_time":0.8294119809,"remaining_time":0.1662806732},
{"learn":[2.280005737],"iteration":833,"passed_time":0.8303723305,"remaining_time":0.1652779459},
{"learn":[2.279137311],"iteration":834,"passed_time":0.8312424441,"remaining_time":0.164257489},
{"learn":[2.277208483],"iteration":835,"passed_time":0.8322134092,"remaining_time":0.163257176},
{"learn":[2.276324814],"iteration":836,"passed_time":0.8332495512,"remaining_time":0.1622696259},
{"learn":[2.272729119],"iteration":837,"passed_time":0.8342648011,"remaining_time":0.161277921},
{"learn":[2.270069715],"iteration":838,"passed_time":0.8351997795,"remaining_time":0.1602707563},
{"learn":[2.268606058],"iteration":839,"passed_time":0.8362025216,"remaining_time":0.1592766708},
{"learn":[2.26697784],"iteration":840,"passed_time":0.8373033145,"remaining_time":0.1583011023},
{"learn":[2.264558128],"iteration":841,"passed_time":0.8383545366,"remaining_time":0.1573159344},
{"learn":[2.262437129],"iteration":842,"passed_time":0.8394455447,"remaining_time":0.1563380196},
{"learn":[2.261248212],"iteration":843,"passed_time":0.8403084576,"remaining_time":0.155317677},
{"learn":[2.260415529],"iteration":844,"passed_time":0.8413592918,"remaining_time":0.1543321778},
{"learn":[2.259070297],"iteration":845,"passed_time":0.8422559855,"remaining_time":0.1533184655},
{"learn":[2.257679194],"iteration":846,"passed_time":0.843179271,"remaining_time":0.1523098329},
{"learn":[2.256851381],"iteration":847,"passed_time":0.8440442698,"remaining_time":0.151290954},
{"learn":[2.254692154],"iteration":848,"passed_time":0.8449691391,"remaining_time":0.150283086},
{"learn":[2.25136586],"iteration":849,"passed_time":0.8458507501,"remaining_time":0.1492677794},
{"learn":[2.248954312],"iteration":850,"passed_time":0.8467622775,"remaining_time":0.1482580251},
{"learn":[2.24731329],"iteration":851,"passed_time":0.847815323,"remaining_time":0.1472730843},
{"learn":[2.246020495],"iteration":852,"passed_time":0.8488121979,"remaining_time":0.1462783037},
{"learn":[2.244931581],"iteration":853,"passed_time":0.849888549,"remaining_time":0.1452971056},
{"learn":[2.242868506],"iteration":854,"passed_time":0.8508454,"remaining_time":0.1442954187},
{"learn":[2.241819887],"iteration":855,"passed_time":0.8517615561,"remaining_time":0.1432869907},
{"learn":[2.238893296],"iteration":856,"passed_time":0.852725032,"remaining_time":0.1422866739},
{"learn":[2.237973458],"iteration":857,"passed_time":0.853638042,"remaining_time":0.1412780909},
{"learn":[2.23693623],"iteration":858,"passed_time":0.8545537819,"remaining_time":0.1402701784},
{"learn":[2.23605034],"iteration":859,"passed_time":0.8555154194,"remaining_time":0.139269952},
{"learn":[2.234870603],"iteration":860,"passed_time":0.8564190095,"remaining_time":0.138260444},
{"learn":[2.233646769],"iteration":861,"passed_time":0.8574074672,"remaining_time":0.1372647685},
{"learn":[2.231157071],"iteration":862,"passed_time":0.8582792481,"remaining_time":0.1362505875},
{"learn":[2.229501942],"iteration":863,"passed_time":0.8591542541,"remaining_time":0.1352372437},
{"learn":[2.228288936],"iteration":864,"passed_time":0.8600265824,"remaining_time":0.1342238019},
{"learn":[2.226192169],"iteration":865,"passed_time":0.8609370833,"remaining_time":0.1332165926},
{"learn":[2.22445021],"iteration":866,"passed_time":0.8619119355,"remaining_time":0.132219478},
{"learn":[2.223295135],"iteration":867,"passed_time":0.8627773222,"remaining_time":0.1312057679},
{"learn":[2.221025544],"iteration":868,"passed_time":0.863776474,"remaining_time":0.130212564},
{"learn":[2.219520846],"iteration":869,"passed_time":0.8646842366,"remaining_time":0.1292056905},
{"learn":[2.218115034],"iteration":870,"passed_time":0.8656359575,"remaining_time":0.1282055551},
{"learn":[2.216418574],"iteration":871,"passed_time":0.8664639075,"remaining_time":0.1271873626},
{"learn":[2.214419352],"iteration":872,"passed_time":0.8673030214,"remaining_time":0.1261712299},
{"learn":[2.211849269],"iteration":873,"passed_time":0.8683593754,"remaining_time":0.1251868207},
{"learn":[2.210688816],"iteration":874,"passed_time":0.8693423597,"remaining_time":0.1241917657},
{"learn":[2.208296925],"iteration":875,"passed_time":0.8702223853,"remaining_time":0.1231821641},
{"learn":[2.205902403],"iteration":876,"passed_time":0.871101859,"remaining_time":0.1221727807},
{"learn":[2.204517397],"iteration":877,"passed_time":0.8720406673,"remaining_time":0.1211719378},
{"learn":[2.20154318],"iteration":878,"passed_time":0.8729680618,"remaining_time":0.1201696649},
{"learn":[2.200501876],"iteration":879,"passed_time":0.873903819,"remaining_time":0.1191687026},
{"learn":[2.199390834],"iteration":880,"passed_time":0.8748694444,"remaining_time":0.1181719227},
{"learn":[2.197851403],"iteration":881,"passed_time":0.875914183,"remaining_time":0.1171857977},
{"learn":[2.196964607],"iteration":882,"passed_time":0.876914825,"remaining_time":0.1161936971},
{"learn":[2.194608111],"iteration":883,"passed_time":0.8779723025,"remaining_time":0.1152090352},
{"learn":[2.191311927],"iteration":884,"passed_time":0.8789197297,"remaining_time":0.1142099084},
{"learn":[2.190287237],"iteration":885,"passed_time":0.8798454054,"remaining_time":0.1132080996},
{"learn":[2.187762109],"iteration":886,"passed_time":0.8807485792,"remaining_time":0.1122035958},
{"learn":[2.18667485],"iteration":887,"passed_time":0.8816111978,"remaining_time":0.1111942051},
{"learn":[2.185798146],"iteration":888,"passed_time":0.8824464986,"remaining_time":0.1101817338},
{"learn":[2.181856918],"iteration":889,"passed_time":0.8833447854,"remaining_time":0.1091774454},
{"learn":[2.180429086],"iteration":890,"passed_time":0.8843031941,"remaining_time":0.1081807499},
{"learn":[2.17935002],"iteration":891,"passed_time":0.8852106639,"remaining_time":0.1071779728},
{"learn":[2.178738269],"iteration":892,"passed_time":0.88607914,"remaining_time":0.1061707368},
{"learn":[2.177598375],"iteration":893,"passed_time":0.886963983,"remaining_time":0.1051657519},
{"learn":[2.175089444],"iteration":894,"passed_time":0.8878730718,"remaining_time":0.1041638799},
{"learn":[2.173727207],"iteration":895,"passed_time":0.8887977725,"remaining_time":0.1031640272},
{"learn":[2.172259065],"iteration":896,"passed_time":0.8897679817,"remaining_time":0.1021695676},
{"learn":[2.171316563],"iteration":897,"passed_time":0.8908753551,"remaining_time":0.1011907419},
{"learn":[2.170711829],"iteration":898,"passed_time":0.8918180347,"remaining_time":0.1001931274},
{"learn":[2.168736269],"iteration":899,"passed_time":0.8927329337,"remaining_time":0.09919254818},
{"learn":[2.166976277],"iteration":900,"passed_time":0.8936100156,"remaining_time":0.09818800393},
{"learn":[2.165619827],"iteration":901,"passed_time":0.8944427867,"remaining_time":0.09717892804},
{"learn":[2.162892065],"iteration":902,"passed_time":0.8953658851,"remaining_time":0.09617994558},
{"learn":[2.161516862],"iteration":903,"passed_time":0.8962352696,"remaining_time":0.09517542686},
{"learn":[2.159721596],"iteration":904,"passed_time":0.8972128049,"remaining_time":0.09418255963},
{"learn":[2.157420063],"iteration":905,"passed_time":0.8981101188,"remaining_time":0.09318140306},
{"learn":[2.155751331],"iteration":906,"passed_time":0.899040227,"remaining_time":0.09218383805},
{"learn":[2.155131799],"iteration":907,"passed_time":0.8999629069,"remaining_time":0.09118566898},
{"learn":[2.152631625],"iteration":908,"passed_time":0.9008277378,"remaining_time":0.09018187475},
{"learn":[2.151021107],"iteration":909,"passed_time":0.9017516013,"remaining_time":0.08918422431},
{"learn":[2.149577685],"iteration":910,"passed_time":0.9026750103,"remaining_time":0.08818669145},
{"learn":[2.147667864],"iteration":911,"passed_time":0.9036575637,"remaining_time":0.08719502807},
{"learn":[2.146477291],"iteration":912,"passed_time":0.9045852471,"remaining_time":0.08619815608},
{"learn":[2.144536596],"iteration":913,"passed_time":0.9055668836,"remaining_time":0.08520651203},
{"learn":[2.143709517],"iteration":914,"passed_time":0.9066092918,"remaining_time":0.0842205353},
{"learn":[2.142748392],"iteration":915,"passed_time":0.9077088539,"remaining_time":0.08323967656},
{"learn":[2.141894595],"iteration":916,"passed_time":0.9086860093,"remaining_time":0.08224747958},
{"learn":[2.140992694],"iteration":917,"passed_time":0.909650072,"remaining_time":0.08125414587},
{"learn":[2.139233045],"iteration":918,"passed_time":0.9105803052,"remaining_time":0.08025789415},
{"learn":[2.136799219],"iteration":919,"passed_time":0.9114854706,"remaining_time":0.07925960614},
{"learn":[2.135463111],"iteration":920,"passed_time":0.9123640305,"remaining_time":0.07825923823},
{"learn":[2.132964634],"iteration":921,"passed_time":0.9133375772,"remaining_time":0.0772671703},
{"learn":[2.131488546],"iteration":922,"passed_time":0.9142419515,"remaining_time":0.0762693719},
{"learn":[2.130256089],"iteration":923,"passed_time":0.9150862522,"remaining_time":0.0752668346},
{"learn":[2.129553906],"iteration":924,"passed_time":0.9159589937,"remaining_time":0.07426694543},
{"learn":[2.128273741],"iteration":925,"passed_time":0.9168562294,"remaining_time":0.07326928831},
{"learn":[2.12682791],"iteration":926,"passed_time":0.9176729503,"remaining_time":0.07226550741},
{"learn":[2.124950727],"iteration":927,"passed_time":0.9185496259,"remaining_time":0.07126678132},
{"learn":[2.124026622],"iteration":928,"passed_time":0.9194845966,"remaining_time":0.07027277326},
{"learn":[2.122626283],"iteration":929,"passed_time":0.9205140266,"remaining_time":0.06928600201},
{"learn":[2.122139101],"iteration":930,"passed_time":0.9214482384,"remaining_time":0.06829208212},
{"learn":[2.120965186],"iteration":931,"passed_time":0.9224077878,"remaining_time":0.06730013902},
{"learn":[2.119810707],"iteration":932,"passed_time":0.9233722234,"remaining_time":0.06630861626},
{"learn":[2.118818495],"iteration":933,"passed_time":0.9243559735,"remaining_time":0.06531851633},
{"learn":[2.117899468],"iteration":934,"passed_time":0.9252852327,"remaining_time":0.06432464184},
{"learn":[2.116022337],"iteration":935,"passed_time":0.9261869323,"remaining_time":0.06332902101},
{"learn":[2.114896411],"iteration":936,"passed_time":0.9271363243,"remaining_time":0.06233680729},
{"learn":[2.113929628],"iteration":937,"passed_time":0.9280142088,"remaining_time":0.06133995837},
{"learn":[2.11338266],"iteration":938,"passed_time":0.9288540587,"remaining_time":0.06034089199},
{"learn":[2.111951077],"iteration":939,"passed_time":0.9297625251,"remaining_time":0.05934654415},
{"learn":[2.110487611],"iteration":940,"passed_time":0.9305544082,"remaining_time":0.05834506916},
{"learn":[2.109169014],"iteration":941,"passed_time":0.9314485408,"remaining_time":0.05735033478},
{"learn":[2.108545473],"iteration":942,"passed_time":0.9322986086,"remaining_time":0.05635315025},
{"learn":[2.105005582],"iteration":943,"passed_time":0.9332058745,"remaining_time":0.05535967052},
{"learn":[2.104134518],"iteration":944,"passed_time":0.9340283701,"remaining_time":0.05436143953},
{"learn":[2.102727023],"iteration":945,"passed_time":0.9349317003,"remaining_time":0.05336819431},
{"learn":[2.101838538],"iteration":946,"passed_time":0.9358666952,"remaining_time":0.05237691114},
{"learn":[2.099510077],"iteration":947,"passed_time":0.9368377197,"remaining_time":0.05138772302},
{"learn":[2.097465484],"iteration":948,"passed_time":0.9377714915,"remaining_time":0.0503965712},
{"learn":[2.096238636],"iteration":949,"passed_time":0.9387424792,"remaining_time":0.04940749891},
{"learn":[2.094902759],"iteration":950,"passed_time":0.9397082442,"remaining_time":0.04841819555},
{"learn":[2.094124482],"iteration":951,"passed_time":0.940618946,"remaining_time":0.04742616534},
{"learn":[2.092008262],"iteration":952,"passed_time":0.9415799856,"remaining_time":0.04643678838},
{"learn":[2.091158024],"iteration":953,"passed_time":0.9424592446,"remaining_time":0.04544352752},
{"learn":[2.089896101],"iteration":954,"passed_time":0.943401948,"remaining_time":0.04445349493},
{"learn":[2.088641804],"iteration":955,"passed_time":0.9442081512,"remaining_time":0.04345727892},
{"learn":[2.086872939],"iteration":956,"passed_time":0.9450609511,"remaining_time":0.04246355371},
{"learn":[2.084627358],"iteration":957,"passed_time":0.9459818498,"remaining_time":0.04147310824},
{"learn":[2.082435484],"iteration":958,"passed_time":0.946996089,"remaining_time":0.04048679838},
{"learn":[2.08127155],"iteration":959,"passed_time":0.9479169903,"remaining_time":0.03949654126},
{"learn":[2.080728959],"iteration":960,"passed_time":0.9487615839,"remaining_time":0.03850333171},
{"learn":[2.079728308],"iteration":961,"passed_time":0.9497128839,"remaining_time":0.03751464614},
{"learn":[2.076828073],"iteration":962,"passed_time":0.9507028353,"remaining_time":0.03652752327},
{"learn":[2.075979822],"iteration":963,"passed_time":0.951709159,"remaining_time":0.03554100594},
{"learn":[2.073601387],"iteration":964,"passed_time":0.9527418835,"remaining_time":0.0345554051},
{"learn":[2.072798108],"iteration":965,"passed_time":0.9536359746,"remaining_time":0.03356482726},
{"learn":[2.071327982],"iteration":966,"passed_time":0.9546972169,"remaining_time":0.03258015321},
{"learn":[2.06965799],"iteration":967,"passed_time":0.9556418191,"remaining_time":0.0315914651},
{"learn":[2.068581001],"iteration":968,"passed_time":0.9566058585,"remaining_time":0.0306034898},
{"learn":[2.066989808],"iteration":969,"passed_time":0.9576287268,"remaining_time":0.0296173833},
{"learn":[2.065978822],"iteration":970,"passed_time":0.9585976405,"remaining_time":0.02862958968},
{"learn":[2.064625623],"iteration":971,"passed_time":0.9594433514,"remaining_time":0.02763828584},
{"learn":[2.063053195],"iteration":972,"passed_time":0.9603752159,"remaining_time":0.02664967197},
{"learn":[2.062555081],"iteration":973,"passed_time":0.961245436,"remaining_time":0.02565952909},
{"learn":[2.060621007],"iteration":974,"passed_time":0.9621927945,"remaining_time":0.02467161012},
{"learn":[2.05908867],"iteration":975,"passed_time":0.9630731759,"remaining_time":0.02368212728},
{"learn":[2.058085815],"iteration":976,"passed_time":0.9639331236,"remaining_time":0.02269238674},
{"learn":[2.056319862],"iteration":977,"passed_time":0.9649674951,"remaining_time":0.02170683527},
{"learn":[2.055074512],"iteration":978,"passed_time":0.9658940701,"remaining_time":0.02071887178},
{"learn":[2.05261822],"iteration":979,"passed_time":0.96681651,"remaining_time":0.01973094918},
{"learn":[2.051343817],"iteration":980,"passed_time":0.9677296626,"remaining_time":0.01874298021},
{"learn":[2.05061869],"iteration":981,"passed_time":0.9686546484,"remaining_time":0.01775538052},
{"learn":[2.048521082],"iteration":982,"passed_time":0.9695148422,"remaining_time":0.01676678771},
{"learn":[2.047723941],"iteration":983,"passed_time":0.9705172792,"remaining_time":0.01578076877},
{"learn":[2.046139291],"iteration":984,"passed_time":0.9715609683,"remaining_time":0.0147953447},
{"learn":[2.045166689],"iteration":985,"passed_time":0.9724430339,"remaining_time":0.01380750758},
{"learn":[2.044056254],"iteration":986,"passed_time":0.9733184431,"remaining_time":0.01281979712},
{"learn":[2.042858005],"iteration":987,"passed_time":0.9742365215,"remaining_time":0.01183283224},
{"learn":[2.041728584],"iteration":988,"passed_time":0.9751074798,"remaining_time":0.01084548259},
{"learn":[2.040839684],"iteration":989,"passed_time":0.9760689158,"remaining_time":0.009859281977},
{"learn":[2.039522176],"iteration":990,"passed_time":0.9770986356,"remaining_time":0.008873751484},
{"learn":[2.038485097],"iteration":991,"passed_time":0.9780507451,"remaining_time":0.007887506009},
{"learn":[2.036192096],"iteration":992,"passed_time":0.9789488605,"remaining_time":0.006900948664},
{"learn":[2.035740102],"iteration":993,"passed_time":0.979973264,"remaining_time":0.005915331573},
{"learn":[2.034680969],"iteration":994,"passed_time":0.9810256854,"remaining_time":0.004929777314},
{"learn":[2.033699188],"iteration":995,"passed_time":0.9819078123,"remaining_time":0.003943404869},
{"learn":[2.031249857],"iteration":996,"passed_time":0.9827589733,"remaining_time":0.002957148365},
{"learn":[2.030075798],"iteration":997,"passed_time":0.9836903195,"remaining_time":0.001971323286},
{"learn":[2.028912879],"iteration":998,"passed_time":0.9846288365,"remaining_time":0.000985614451},
{"learn":[2.02858943],"iteration":999,"passed_time":0.985550958,"remaining_time":0}
]}